{
  "fetched_at": "2026-05-28 16:49 UTC",
  "ticker": "MSTR",
  "option_type": "put",
  "strike": 130.0,
  "range": 5.0,
  "current_price": 148.6,
  "hv_context": {
    "currentHV": 0.720681,
    "hvPct": 85,
    "hvMin": 0.445362,
    "hvMax": 1.172094
  },
  "avg_iv": 0.7336,
  "contracts": [
    {
      "option_type": "put",
      "expiration_date": "2026-05-29",
      "dte": 1,
      "strike": 125.0,
      "bid": 0.04,
      "ask": 0.05,
      "mid": 0.045,
      "premium_per_day": 0.045,
      "delta_from_price": -23.6,
      "open_interest": 9455,
      "volume": 1173,
      "implied_volatility": 1.039067,
      "iv_vs_hv": 1.4418,
      "in_the_money": false
    },
    {
      "option_type": "put",
      "expiration_date": "2026-05-29",
      "dte": 1,
      "strike": 126.0,
      "bid": 0.01,
      "ask": 0.13,
      "mid": 0.07,
      "premium_per_day": 0.07,
      "delta_from_price": -22.6,
      "open_interest": 123,
      "volume": 55,
      "implied_volatility": 1.062505,
      "iv_vs_hv": 1.4743,
      "in_the_money": false
    },
    {
      "option_type": "put",
      "expiration_date": "2026-05-29",
      "dte": 1,
      "strike": 127.0,
      "bid": 0.01,
      "ask": 0.12,
      "mid": 0.065,
      "premium_per_day": 0.065,
      "delta_from_price": -21.6,
      "open_interest": 192,
      "volume": 159,
      "implied_volatility": 1.007817,
      "iv_vs_hv": 1.3984,
      "in_the_money": false
    },
    {
      "option_type": "put",
      "expiration_date": "2026-05-29",
      "dte": 1,
      "strike": 128.0,
      "bid": 0.05,
      "ask": 0.09,
      "mid": 0.07,
      "premium_per_day": 0.07,
      "delta_from_price": -20.6,
      "open_interest": 283,
      "volume": 225,
      "implied_volatility": 0.972657,
      "iv_vs_hv": 1.3496,
      "in_the_money": false
    },
    {
      "option_type": "put",
      "expiration_date": "2026-05-29",
      "dte": 1,
      "strike": 129.0,
      "bid": 0.01,
      "ask": 0.15,
      "mid": 0.08,
      "premium_per_day": 0.08,
      "delta_from_price": -19.6,
      "open_interest": 601,
      "volume": 219,
      "implied_volatility": 0.949219,
      "iv_vs_hv": 1.3171,
      "in_the_money": false
    },
    {
      "option_type": "put",
      "expiration_date": "2026-05-29",
      "dte": 1,
      "strike": 130.0,
      "bid": 0.05,
      "ask": 0.07,
      "mid": 0.06,
      "premium_per_day": 0.06,
      "delta_from_price": -18.6,
      "open_interest": 3175,
      "volume": 1111,
      "implied_volatility": 0.867189,
      "iv_vs_hv": 1.2033,
      "in_the_money": false
    },
    {
      "option_type": "put",
      "expiration_date": "2026-05-29",
      "dte": 1,
      "strike": 131.0,
      "bid": 0.01,
      "ask": 0.1,
      "mid": 0.055,
      "premium_per_day": 0.055,
      "delta_from_price": -17.6,
      "open_interest": 224,
      "volume": 95,
      "implied_volatility": 0.812502,
      "iv_vs_hv": 1.1274,
      "in_the_money": false
    },
    {
      "option_type": "put",
      "expiration_date": "2026-05-29",
      "dte": 1,
      "strike": 132.0,
      "bid": 0.05,
      "ask": 0.15,
      "mid": 0.1,
      "premium_per_day": 0.1,
      "delta_from_price": -16.6,
      "open_interest": 105,
      "volume": 11,
      "implied_volatility": 0.847658,
      "iv_vs_hv": 1.1762,
      "in_the_money": false
    },
    {
      "option_type": "put",
      "expiration_date": "2026-05-29",
      "dte": 1,
      "strike": 133.0,
      "bid": 0.02,
      "ask": 0.18,
      "mid": 0.1,
      "premium_per_day": 0.1,
      "delta_from_price": -15.6,
      "open_interest": 438,
      "volume": 698,
      "implied_volatility": 0.800783,
      "iv_vs_hv": 1.1111,
      "in_the_money": false
    },
    {
      "option_type": "put",
      "expiration_date": "2026-05-29",
      "dte": 1,
      "strike": 134.0,
      "bid": 0.0,
      "ask": 0.22,
      "mid": 0.11,
      "premium_per_day": 0.11,
      "delta_from_price": -14.6,
      "open_interest": 1174,
      "volume": 261,
      "implied_volatility": 0.769534,
      "iv_vs_hv": 1.0678,
      "in_the_money": false
    },
    {
      "option_type": "put",
      "expiration_date": "2026-05-29",
      "dte": 1,
      "strike": 135.0,
      "bid": 0.1,
      "ask": 0.13,
      "mid": 0.115,
      "premium_per_day": 0.115,
      "delta_from_price": -13.6,
      "open_interest": 2331,
      "volume": 1990,
      "implied_volatility": 0.728518,
      "iv_vs_hv": 1.0109,
      "in_the_money": false
    },
    {
      "option_type": "put",
      "expiration_date": "2026-06-05",
      "dte": 8,
      "strike": 125.0,
      "bid": 0.5,
      "ask": 0.58,
      "mid": 0.54,
      "premium_per_day": 0.0675,
      "delta_from_price": -23.6,
      "open_interest": 4592,
      "volume": 1269,
      "implied_volatility": 0.761721,
      "iv_vs_hv": 1.0569,
      "in_the_money": false
    },
    {
      "option_type": "put",
      "expiration_date": "2026-06-05",
      "dte": 8,
      "strike": 126.0,
      "bid": 0.54,
      "ask": 0.71,
      "mid": 0.625,
      "premium_per_day": 0.078125,
      "delta_from_price": -22.6,
      "open_interest": 51,
      "volume": 85,
      "implied_volatility": 0.760745,
      "iv_vs_hv": 1.0556,
      "in_the_money": false
    },
    {
      "option_type": "put",
      "expiration_date": "2026-06-05",
      "dte": 8,
      "strike": 127.0,
      "bid": 0.61,
      "ask": 0.74,
      "mid": 0.675,
      "premium_per_day": 0.084375,
      "delta_from_price": -21.6,
      "open_interest": 44,
      "volume": 27,
      "implied_volatility": 0.747073,
      "iv_vs_hv": 1.0366,
      "in_the_money": false
    },
    {
      "option_type": "put",
      "expiration_date": "2026-06-05",
      "dte": 8,
      "strike": 128.0,
      "bid": 0.67,
      "ask": 0.79,
      "mid": 0.73,
      "premium_per_day": 0.09125,
      "delta_from_price": -20.6,
      "open_interest": 420,
      "volume": 20,
      "implied_volatility": 0.733401,
      "iv_vs_hv": 1.0177,
      "in_the_money": false
    },
    {
      "option_type": "put",
      "expiration_date": "2026-06-05",
      "dte": 8,
      "strike": 129.0,
      "bid": 0.75,
      "ask": 0.82,
      "mid": 0.785,
      "premium_per_day": 0.098125,
      "delta_from_price": -19.6,
      "open_interest": 27,
      "volume": 25,
      "implied_volatility": 0.718753,
      "iv_vs_hv": 0.9973,
      "in_the_money": false
    },
    {
      "option_type": "put",
      "expiration_date": "2026-06-05",
      "dte": 8,
      "strike": 130.0,
      "bid": 0.84,
      "ask": 0.89,
      "mid": 0.865,
      "premium_per_day": 0.108125,
      "delta_from_price": -18.6,
      "open_interest": 2248,
      "volume": 1208,
      "implied_volatility": 0.708987,
      "iv_vs_hv": 0.9838,
      "in_the_money": false
    },
    {
      "option_type": "put",
      "expiration_date": "2026-06-05",
      "dte": 8,
      "strike": 131.0,
      "bid": 0.92,
      "ask": 1.06,
      "mid": 0.99,
      "premium_per_day": 0.12375,
      "delta_from_price": -17.6,
      "open_interest": 40,
      "volume": 3213,
      "implied_volatility": 0.707034,
      "iv_vs_hv": 0.9811,
      "in_the_money": false
    },
    {
      "option_type": "put",
      "expiration_date": "2026-06-05",
      "dte": 8,
      "strike": 132.0,
      "bid": 1.03,
      "ask": 1.18,
      "mid": 1.105,
      "premium_per_day": 0.138125,
      "delta_from_price": -16.6,
      "open_interest": 280,
      "volume": 78,
      "implied_volatility": 0.700198,
      "iv_vs_hv": 0.9716,
      "in_the_money": false
    },
    {
      "option_type": "put",
      "expiration_date": "2026-06-05",
      "dte": 8,
      "strike": 133.0,
      "bid": 1.09,
      "ask": 1.27,
      "mid": 1.18,
      "premium_per_day": 0.1475,
      "delta_from_price": -15.6,
      "open_interest": 424,
      "volume": 58,
      "implied_volatility": 0.683597,
      "iv_vs_hv": 0.9485,
      "in_the_money": false
    },
    {
      "option_type": "put",
      "expiration_date": "2026-06-05",
      "dte": 8,
      "strike": 134.0,
      "bid": 1.29,
      "ask": 1.44,
      "mid": 1.365,
      "premium_per_day": 0.170625,
      "delta_from_price": -14.6,
      "open_interest": 38,
      "volume": 79,
      "implied_volatility": 0.686038,
      "iv_vs_hv": 0.9519,
      "in_the_money": false
    },
    {
      "option_type": "put",
      "expiration_date": "2026-06-05",
      "dte": 8,
      "strike": 135.0,
      "bid": 1.41,
      "ask": 1.52,
      "mid": 1.465,
      "premium_per_day": 0.183125,
      "delta_from_price": -13.6,
      "open_interest": 957,
      "volume": 1181,
      "implied_volatility": 0.670413,
      "iv_vs_hv": 0.9302,
      "in_the_money": false
    },
    {
      "option_type": "put",
      "expiration_date": "2026-06-12",
      "dte": 15,
      "strike": 125.0,
      "bid": 1.23,
      "ask": 1.4,
      "mid": 1.315,
      "premium_per_day": 0.087667,
      "delta_from_price": -23.6,
      "open_interest": 2315,
      "volume": 60,
      "implied_volatility": 0.725589,
      "iv_vs_hv": 1.0068,
      "in_the_money": false
    },
    {
      "option_type": "put",
      "expiration_date": "2026-06-12",
      "dte": 15,
      "strike": 130.0,
      "bid": 1.85,
      "ask": 2.02,
      "mid": 1.935,
      "premium_per_day": 0.129,
      "delta_from_price": -18.6,
      "open_interest": 970,
      "volume": 586,
      "implied_volatility": 0.691898,
      "iv_vs_hv": 0.9601,
      "in_the_money": false
    },
    {
      "option_type": "put",
      "expiration_date": "2026-06-12",
      "dte": 15,
      "strike": 135.0,
      "bid": 2.8,
      "ask": 3.05,
      "mid": 2.925,
      "premium_per_day": 0.195,
      "delta_from_price": -13.6,
      "open_interest": 318,
      "volume": 612,
      "implied_volatility": 0.67139,
      "iv_vs_hv": 0.9316,
      "in_the_money": false
    },
    {
      "option_type": "put",
      "expiration_date": "2026-06-18",
      "dte": 21,
      "strike": 125.0,
      "bid": 1.89,
      "ask": 2.01,
      "mid": 1.95,
      "premium_per_day": 0.092857,
      "delta_from_price": -23.6,
      "open_interest": 6731,
      "volume": 143,
      "implied_volatility": 0.703128,
      "iv_vs_hv": 0.9756,
      "in_the_money": false
    },
    {
      "option_type": "put",
      "expiration_date": "2026-06-18",
      "dte": 21,
      "strike": 126.0,
      "bid": 2.02,
      "ask": 2.17,
      "mid": 2.095,
      "premium_per_day": 0.099762,
      "delta_from_price": -22.6,
      "open_interest": 415,
      "volume": 277,
      "implied_volatility": 0.698245,
      "iv_vs_hv": 0.9689,
      "in_the_money": false
    },
    {
      "option_type": "put",
      "expiration_date": "2026-06-18",
      "dte": 21,
      "strike": 127.0,
      "bid": 2.16,
      "ask": 2.3,
      "mid": 2.23,
      "premium_per_day": 0.10619,
      "delta_from_price": -21.6,
      "open_interest": 378,
      "volume": 10,
      "implied_volatility": 0.691409,
      "iv_vs_hv": 0.9594,
      "in_the_money": false
    },
    {
      "option_type": "put",
      "expiration_date": "2026-06-18",
      "dte": 21,
      "strike": 128.0,
      "bid": 2.34,
      "ask": 2.47,
      "mid": 2.405,
      "premium_per_day": 0.114524,
      "delta_from_price": -20.6,
      "open_interest": 384,
      "volume": 15,
      "implied_volatility": 0.687747,
      "iv_vs_hv": 0.9543,
      "in_the_money": false
    },
    {
      "option_type": "put",
      "expiration_date": "2026-06-18",
      "dte": 21,
      "strike": 129.0,
      "bid": 2.52,
      "ask": 2.65,
      "mid": 2.585,
      "premium_per_day": 0.123095,
      "delta_from_price": -19.6,
      "open_interest": 260,
      "volume": 62,
      "implied_volatility": 0.683719,
      "iv_vs_hv": 0.9487,
      "in_the_money": false
    },
    {
      "option_type": "put",
      "expiration_date": "2026-06-18",
      "dte": 21,
      "strike": 130.0,
      "bid": 2.7,
      "ask": 2.85,
      "mid": 2.775,
      "premium_per_day": 0.132143,
      "delta_from_price": -18.6,
      "open_interest": 9117,
      "volume": 1889,
      "implied_volatility": 0.679569,
      "iv_vs_hv": 0.943,
      "in_the_money": false
    },
    {
      "option_type": "put",
      "expiration_date": "2026-06-18",
      "dte": 21,
      "strike": 131.0,
      "bid": 2.91,
      "ask": 3.05,
      "mid": 2.98,
      "premium_per_day": 0.141905,
      "delta_from_price": -17.6,
      "open_interest": 249,
      "volume": 5,
      "implied_volatility": 0.675784,
      "iv_vs_hv": 0.9377,
      "in_the_money": false
    },
    {
      "option_type": "put",
      "expiration_date": "2026-06-18",
      "dte": 21,
      "strike": 132.0,
      "bid": 3.1,
      "ask": 3.25,
      "mid": 3.175,
      "premium_per_day": 0.15119,
      "delta_from_price": -16.6,
      "open_interest": 599,
      "volume": 24,
      "implied_volatility": 0.669925,
      "iv_vs_hv": 0.9296,
      "in_the_money": false
    },
    {
      "option_type": "put",
      "expiration_date": "2026-06-18",
      "dte": 21,
      "strike": 133.0,
      "bid": 3.4,
      "ask": 3.5,
      "mid": 3.45,
      "premium_per_day": 0.164286,
      "delta_from_price": -15.6,
      "open_interest": 1001,
      "volume": 58,
      "implied_volatility": 0.670413,
      "iv_vs_hv": 0.9302,
      "in_the_money": false
    },
    {
      "option_type": "put",
      "expiration_date": "2026-06-18",
      "dte": 21,
      "strike": 134.0,
      "bid": 3.55,
      "ask": 3.7,
      "mid": 3.625,
      "premium_per_day": 0.172619,
      "delta_from_price": -14.6,
      "open_interest": 1350,
      "volume": 73,
      "implied_volatility": 0.660648,
      "iv_vs_hv": 0.9167,
      "in_the_money": false
    },
    {
      "option_type": "put",
      "expiration_date": "2026-06-18",
      "dte": 21,
      "strike": 135.0,
      "bid": 3.85,
      "ask": 4.05,
      "mid": 3.95,
      "premium_per_day": 0.188095,
      "delta_from_price": -13.6,
      "open_interest": 4306,
      "volume": 2381,
      "implied_volatility": 0.663089,
      "iv_vs_hv": 0.9201,
      "in_the_money": false
    },
    {
      "option_type": "put",
      "expiration_date": "2026-06-26",
      "dte": 29,
      "strike": 125.0,
      "bid": 2.77,
      "ask": 3.0,
      "mid": 2.885,
      "premium_per_day": 0.099483,
      "delta_from_price": -23.6,
      "open_interest": 236,
      "volume": 104,
      "implied_volatility": 0.695193,
      "iv_vs_hv": 0.9646,
      "in_the_money": false
    },
    {
      "option_type": "put",
      "expiration_date": "2026-06-26",
      "dte": 29,
      "strike": 130.0,
      "bid": 3.5,
      "ask": 3.9,
      "mid": 3.7,
      "premium_per_day": 0.127586,
      "delta_from_price": -18.6,
      "open_interest": 668,
      "volume": 288,
      "implied_volatility": 0.659427,
      "iv_vs_hv": 0.915,
      "in_the_money": false
    },
    {
      "option_type": "put",
      "expiration_date": "2026-06-26",
      "dte": 29,
      "strike": 135.0,
      "bid": 4.7,
      "ask": 5.25,
      "mid": 4.975,
      "premium_per_day": 0.171552,
      "delta_from_price": -13.6,
      "open_interest": 127,
      "volume": 199,
      "implied_volatility": 0.641971,
      "iv_vs_hv": 0.8908,
      "in_the_money": false
    },
    {
      "option_type": "put",
      "expiration_date": "2026-07-02",
      "dte": 35,
      "strike": 130.0,
      "bid": 3.85,
      "ask": 5.0,
      "mid": 4.425,
      "premium_per_day": 0.126429,
      "delta_from_price": -18.6,
      "open_interest": 93,
      "volume": 74,
      "implied_volatility": 0.654667,
      "iv_vs_hv": 0.9084,
      "in_the_money": false
    },
    {
      "option_type": "put",
      "expiration_date": "2026-07-02",
      "dte": 35,
      "strike": 135.0,
      "bid": 5.3,
      "ask": 6.9,
      "mid": 6.1,
      "premium_per_day": 0.174286,
      "delta_from_price": -13.6,
      "open_interest": 14,
      "volume": 7,
      "implied_volatility": 0.657962,
      "iv_vs_hv": 0.913,
      "in_the_money": false
    },
    {
      "option_type": "put",
      "expiration_date": "2026-07-17",
      "dte": 50,
      "strike": 125.0,
      "bid": 4.95,
      "ask": 5.15,
      "mid": 5.05,
      "premium_per_day": 0.101,
      "delta_from_price": -23.6,
      "open_interest": 882,
      "volume": 118,
      "implied_volatility": 0.677249,
      "iv_vs_hv": 0.9397,
      "in_the_money": false
    },
    {
      "option_type": "put",
      "expiration_date": "2026-07-17",
      "dte": 50,
      "strike": 130.0,
      "bid": 6.4,
      "ask": 6.65,
      "mid": 6.525,
      "premium_per_day": 0.1305,
      "delta_from_price": -18.6,
      "open_interest": 2754,
      "volume": 512,
      "implied_volatility": 0.671268,
      "iv_vs_hv": 0.9314,
      "in_the_money": false
    },
    {
      "option_type": "put",
      "expiration_date": "2026-07-17",
      "dte": 50,
      "strike": 135.0,
      "bid": 7.95,
      "ask": 8.35,
      "mid": 8.15,
      "premium_per_day": 0.163,
      "delta_from_price": -13.6,
      "open_interest": 1268,
      "volume": 240,
      "implied_volatility": 0.659671,
      "iv_vs_hv": 0.9153,
      "in_the_money": false
    },
    {
      "option_type": "put",
      "expiration_date": "2026-08-21",
      "dte": 85,
      "strike": 125.0,
      "bid": 9.1,
      "ask": 9.75,
      "mid": 9.425,
      "premium_per_day": 0.110882,
      "delta_from_price": -23.6,
      "open_interest": 1193,
      "volume": 30,
      "implied_volatility": 0.720035,
      "iv_vs_hv": 0.9991,
      "in_the_money": false
    },
    {
      "option_type": "put",
      "expiration_date": "2026-08-21",
      "dte": 85,
      "strike": 130.0,
      "bid": 10.85,
      "ask": 11.05,
      "mid": 10.95,
      "premium_per_day": 0.128824,
      "delta_from_price": -18.6,
      "open_interest": 1464,
      "volume": 130,
      "implied_volatility": 0.701541,
      "iv_vs_hv": 0.9734,
      "in_the_money": false
    },
    {
      "option_type": "put",
      "expiration_date": "2026-08-21",
      "dte": 85,
      "strike": 135.0,
      "bid": 12.75,
      "ask": 13.05,
      "mid": 12.9,
      "premium_per_day": 0.151765,
      "delta_from_price": -13.6,
      "open_interest": 1077,
      "volume": 44,
      "implied_volatility": 0.693057,
      "iv_vs_hv": 0.9617,
      "in_the_money": false
    },
    {
      "option_type": "put",
      "expiration_date": "2026-09-18",
      "dte": 113,
      "strike": 125.0,
      "bid": 11.65,
      "ask": 12.15,
      "mid": 11.9,
      "premium_per_day": 0.10531,
      "delta_from_price": -23.6,
      "open_interest": 744,
      "volume": 12,
      "implied_volatility": 0.717654,
      "iv_vs_hv": 0.9958,
      "in_the_money": false
    },
    {
      "option_type": "put",
      "expiration_date": "2026-09-18",
      "dte": 113,
      "strike": 130.0,
      "bid": 13.55,
      "ask": 14.05,
      "mid": 13.8,
      "premium_per_day": 0.122124,
      "delta_from_price": -18.6,
      "open_interest": 960,
      "volume": 35,
      "implied_volatility": 0.709292,
      "iv_vs_hv": 0.9842,
      "in_the_money": false
    },
    {
      "option_type": "put",
      "expiration_date": "2026-09-18",
      "dte": 113,
      "strike": 135.0,
      "bid": 15.75,
      "ask": 16.15,
      "mid": 15.95,
      "premium_per_day": 0.14115,
      "delta_from_price": -13.6,
      "open_interest": 726,
      "volume": 176,
      "implied_volatility": 0.703677,
      "iv_vs_hv": 0.9764,
      "in_the_money": false
    },
    {
      "option_type": "put",
      "expiration_date": "2026-10-16",
      "dte": 141,
      "strike": 125.0,
      "bid": 14.0,
      "ask": 14.5,
      "mid": 14.25,
      "premium_per_day": 0.101064,
      "delta_from_price": -23.6,
      "open_interest": 347,
      "volume": 19,
      "implied_volatility": 0.720035,
      "iv_vs_hv": 0.9991,
      "in_the_money": false
    },
    {
      "option_type": "put",
      "expiration_date": "2026-10-16",
      "dte": 141,
      "strike": 130.0,
      "bid": 16.05,
      "ask": 16.7,
      "mid": 16.375,
      "premium_per_day": 0.116135,
      "delta_from_price": -18.6,
      "open_interest": 377,
      "volume": 3,
      "implied_volatility": 0.715579,
      "iv_vs_hv": 0.9929,
      "in_the_money": false
    },
    {
      "option_type": "put",
      "expiration_date": "2026-10-16",
      "dte": 141,
      "strike": 135.0,
      "bid": 18.3,
      "ask": 18.85,
      "mid": 18.575,
      "premium_per_day": 0.131738,
      "delta_from_price": -13.6,
      "open_interest": 654,
      "volume": 23,
      "implied_volatility": 0.708682,
      "iv_vs_hv": 0.9834,
      "in_the_money": false
    },
    {
      "option_type": "put",
      "expiration_date": "2026-11-20",
      "dte": 176,
      "strike": 125.0,
      "bid": 16.95,
      "ask": 17.65,
      "mid": 17.3,
      "premium_per_day": 0.098295,
      "delta_from_price": -23.6,
      "open_interest": 54,
      "volume": 3,
      "implied_volatility": 0.733462,
      "iv_vs_hv": 1.0177,
      "in_the_money": false
    },
    {
      "option_type": "put",
      "expiration_date": "2026-11-20",
      "dte": 176,
      "strike": 130.0,
      "bid": 19.15,
      "ask": 19.8,
      "mid": 19.475,
      "premium_per_day": 0.110653,
      "delta_from_price": -18.6,
      "open_interest": 151,
      "volume": 1,
      "implied_volatility": 0.726931,
      "iv_vs_hv": 1.0087,
      "in_the_money": false
    },
    {
      "option_type": "put",
      "expiration_date": "2026-11-20",
      "dte": 176,
      "strike": 135.0,
      "bid": 21.45,
      "ask": 22.15,
      "mid": 21.8,
      "premium_per_day": 0.123864,
      "delta_from_price": -13.6,
      "open_interest": 29,
      "volume": 3,
      "implied_volatility": 0.720828,
      "iv_vs_hv": 1.0002,
      "in_the_money": false
    },
    {
      "option_type": "put",
      "expiration_date": "2026-12-18",
      "dte": 204,
      "strike": 125.0,
      "bid": 19.1,
      "ask": 19.65,
      "mid": 19.375,
      "premium_per_day": 0.094975,
      "delta_from_price": -23.6,
      "open_interest": 646,
      "volume": 5,
      "implied_volatility": 0.737155,
      "iv_vs_hv": 1.0229,
      "in_the_money": false
    },
    {
      "option_type": "put",
      "expiration_date": "2026-12-18",
      "dte": 204,
      "strike": 130.0,
      "bid": 21.35,
      "ask": 21.95,
      "mid": 21.65,
      "premium_per_day": 0.106127,
      "delta_from_price": -18.6,
      "open_interest": 2104,
      "volume": 21,
      "implied_volatility": 0.731448,
      "iv_vs_hv": 1.0149,
      "in_the_money": false
    },
    {
      "option_type": "put",
      "expiration_date": "2026-12-18",
      "dte": 204,
      "strike": 135.0,
      "bid": 23.8,
      "ask": 24.45,
      "mid": 24.125,
      "premium_per_day": 0.11826,
      "delta_from_price": -13.6,
      "open_interest": 689,
      "volume": 28,
      "implied_volatility": 0.727603,
      "iv_vs_hv": 1.0096,
      "in_the_money": false
    },
    {
      "option_type": "put",
      "expiration_date": "2027-01-15",
      "dte": 232,
      "strike": 125.0,
      "bid": 20.9,
      "ask": 21.55,
      "mid": 21.225,
      "premium_per_day": 0.091487,
      "delta_from_price": -23.6,
      "open_interest": 719,
      "volume": 3,
      "implied_volatility": 0.737918,
      "iv_vs_hv": 1.0239,
      "in_the_money": false
    },
    {
      "option_type": "put",
      "expiration_date": "2027-01-15",
      "dte": 232,
      "strike": 130.0,
      "bid": 23.3,
      "ask": 23.8,
      "mid": 23.55,
      "premium_per_day": 0.101509,
      "delta_from_price": -18.6,
      "open_interest": 854,
      "volume": 6,
      "implied_volatility": 0.731997,
      "iv_vs_hv": 1.0157,
      "in_the_money": false
    },
    {
      "option_type": "put",
      "expiration_date": "2027-01-15",
      "dte": 232,
      "strike": 135.0,
      "bid": 25.7,
      "ask": 26.45,
      "mid": 26.075,
      "premium_per_day": 0.112392,
      "delta_from_price": -13.6,
      "open_interest": 987,
      "volume": 16,
      "implied_volatility": 0.728091,
      "iv_vs_hv": 1.0103,
      "in_the_money": false
    },
    {
      "option_type": "put",
      "expiration_date": "2027-03-19",
      "dte": 295,
      "strike": 125.0,
      "bid": 24.1,
      "ask": 26.0,
      "mid": 25.05,
      "premium_per_day": 0.084915,
      "delta_from_price": -23.6,
      "open_interest": 229,
      "volume": 1,
      "implied_volatility": 0.739962,
      "iv_vs_hv": 1.0268,
      "in_the_money": false
    },
    {
      "option_type": "put",
      "expiration_date": "2027-03-19",
      "dte": 295,
      "strike": 130.0,
      "bid": 25.9,
      "ask": 28.8,
      "mid": 27.35,
      "premium_per_day": 0.092712,
      "delta_from_price": -18.6,
      "open_interest": 183,
      "volume": 1,
      "implied_volatility": 0.731204,
      "iv_vs_hv": 1.0146,
      "in_the_money": false
    },
    {
      "option_type": "put",
      "expiration_date": "2027-03-19",
      "dte": 295,
      "strike": 135.0,
      "bid": 29.1,
      "ask": 30.95,
      "mid": 30.025,
      "premium_per_day": 0.10178,
      "delta_from_price": -13.6,
      "open_interest": 44,
      "volume": 20,
      "implied_volatility": 0.728457,
      "iv_vs_hv": 1.0108,
      "in_the_money": false
    },
    {
      "option_type": "put",
      "expiration_date": "2027-06-17",
      "dte": 385,
      "strike": 125.0,
      "bid": 28.8,
      "ask": 31.55,
      "mid": 30.175,
      "premium_per_day": 0.078377,
      "delta_from_price": -23.6,
      "open_interest": 933,
      "volume": 158,
      "implied_volatility": 0.74869,
      "iv_vs_hv": 1.0389,
      "in_the_money": false
    },
    {
      "option_type": "put",
      "expiration_date": "2027-06-17",
      "dte": 385,
      "strike": 130.0,
      "bid": 31.35,
      "ask": 33.5,
      "mid": 32.425,
      "premium_per_day": 0.084221,
      "delta_from_price": -18.6,
      "open_interest": 141,
      "volume": 36,
      "implied_volatility": 0.73685,
      "iv_vs_hv": 1.0224,
      "in_the_money": false
    },
    {
      "option_type": "put",
      "expiration_date": "2027-06-17",
      "dte": 385,
      "strike": 135.0,
      "bid": 33.85,
      "ask": 35.85,
      "mid": 34.85,
      "premium_per_day": 0.090519,
      "delta_from_price": -13.6,
      "open_interest": 184,
      "volume": 3,
      "implied_volatility": 0.727084,
      "iv_vs_hv": 1.0089,
      "in_the_money": false
    },
    {
      "option_type": "put",
      "expiration_date": "2027-09-17",
      "dte": 477,
      "strike": 125.0,
      "bid": 32.0,
      "ask": 35.55,
      "mid": 33.775,
      "premium_per_day": 0.070807,
      "delta_from_price": -23.6,
      "open_interest": 142,
      "volume": 1,
      "implied_volatility": 0.737063,
      "iv_vs_hv": 1.0227,
      "in_the_money": false
    },
    {
      "option_type": "put",
      "expiration_date": "2027-09-17",
      "dte": 477,
      "strike": 130.0,
      "bid": 34.95,
      "ask": 37.95,
      "mid": 36.45,
      "premium_per_day": 0.076415,
      "delta_from_price": -18.6,
      "open_interest": 493,
      "volume": 20,
      "implied_volatility": 0.731845,
      "iv_vs_hv": 1.0155,
      "in_the_money": false
    },
    {
      "option_type": "put",
      "expiration_date": "2027-09-17",
      "dte": 477,
      "strike": 135.0,
      "bid": 37.8,
      "ask": 40.75,
      "mid": 39.275,
      "premium_per_day": 0.082338,
      "delta_from_price": -13.6,
      "open_interest": 79,
      "volume": 50,
      "implied_volatility": 0.727969,
      "iv_vs_hv": 1.0101,
      "in_the_money": false
    },
    {
      "option_type": "put",
      "expiration_date": "2027-12-17",
      "dte": 568,
      "strike": 125.0,
      "bid": 35.4,
      "ask": 39.0,
      "mid": 37.2,
      "premium_per_day": 0.065493,
      "delta_from_price": -23.6,
      "open_interest": 427,
      "volume": 100,
      "implied_volatility": 0.732241,
      "iv_vs_hv": 1.016,
      "in_the_money": false
    },
    {
      "option_type": "put",
      "expiration_date": "2027-12-17",
      "dte": 568,
      "strike": 130.0,
      "bid": 38.2,
      "ask": 41.35,
      "mid": 39.775,
      "premium_per_day": 0.070026,
      "delta_from_price": -18.6,
      "open_interest": 273,
      "volume": 30,
      "implied_volatility": 0.724246,
      "iv_vs_hv": 1.0049,
      "in_the_money": false
    },
    {
      "option_type": "put",
      "expiration_date": "2027-12-17",
      "dte": 568,
      "strike": 135.0,
      "bid": 40.85,
      "ask": 45.45,
      "mid": 43.15,
      "premium_per_day": 0.075968,
      "delta_from_price": -13.6,
      "open_interest": 380,
      "volume": 3,
      "implied_volatility": 0.72803,
      "iv_vs_hv": 1.0102,
      "in_the_money": false
    },
    {
      "option_type": "put",
      "expiration_date": "2028-01-21",
      "dte": 603,
      "strike": 125.0,
      "bid": 36.6,
      "ask": 40.15,
      "mid": 38.375,
      "premium_per_day": 0.06364,
      "delta_from_price": -23.6,
      "open_interest": 100,
      "volume": 2,
      "implied_volatility": 0.72977,
      "iv_vs_hv": 1.0126,
      "in_the_money": false
    },
    {
      "option_type": "put",
      "expiration_date": "2028-01-21",
      "dte": 603,
      "strike": 130.0,
      "bid": 41.15,
      "ask": 42.4,
      "mid": 41.775,
      "premium_per_day": 0.069279,
      "delta_from_price": -18.6,
      "open_interest": 448,
      "volume": 1,
      "implied_volatility": 0.7345,
      "iv_vs_hv": 1.0192,
      "in_the_money": false
    },
    {
      "option_type": "put",
      "expiration_date": "2028-01-21",
      "dte": 603,
      "strike": 135.0,
      "bid": 44.05,
      "ask": 45.8,
      "mid": 44.925,
      "premium_per_day": 0.074502,
      "delta_from_price": -13.6,
      "open_interest": 519,
      "volume": 2,
      "implied_volatility": 0.73395,
      "iv_vs_hv": 1.0184,
      "in_the_money": false
    },
    {
      "option_type": "put",
      "expiration_date": "2028-06-16",
      "dte": 750,
      "strike": 125.0,
      "bid": 40.0,
      "ask": 48.0,
      "mid": 44.0,
      "premium_per_day": 0.058667,
      "delta_from_price": -23.6,
      "open_interest": 338,
      "volume": 4,
      "implied_volatility": 0.73746,
      "iv_vs_hv": 1.0233,
      "in_the_money": false
    },
    {
      "option_type": "put",
      "expiration_date": "2028-06-16",
      "dte": 750,
      "strike": 130.0,
      "bid": 44.95,
      "ask": 48.1,
      "mid": 46.525,
      "premium_per_day": 0.062033,
      "delta_from_price": -18.6,
      "open_interest": 100,
      "volume": 1,
      "implied_volatility": 0.726962,
      "iv_vs_hv": 1.0087,
      "in_the_money": false
    },
    {
      "option_type": "put",
      "expiration_date": "2028-06-16",
      "dte": 750,
      "strike": 135.0,
      "bid": 47.05,
      "ask": 51.2,
      "mid": 49.125,
      "premium_per_day": 0.0655,
      "delta_from_price": -13.6,
      "open_interest": 332,
      "volume": 1,
      "implied_volatility": 0.717074,
      "iv_vs_hv": 0.995,
      "in_the_money": false
    },
    {
      "option_type": "put",
      "expiration_date": "2028-12-15",
      "dte": 932,
      "strike": 125.0,
      "bid": 45.9,
      "ask": 49.35,
      "mid": 47.625,
      "premium_per_day": 0.0511,
      "delta_from_price": -23.6,
      "open_interest": 50,
      "volume": 2,
      "implied_volatility": 0.710757,
      "iv_vs_hv": 0.9862,
      "in_the_money": false
    },
    {
      "option_type": "put",
      "expiration_date": "2028-12-15",
      "dte": 932,
      "strike": 130.0,
      "bid": 48.95,
      "ask": 52.45,
      "mid": 50.7,
      "premium_per_day": 0.054399,
      "delta_from_price": -18.6,
      "open_interest": 115,
      "volume": 15,
      "implied_volatility": 0.707278,
      "iv_vs_hv": 0.9814,
      "in_the_money": false
    },
    {
      "option_type": "put",
      "expiration_date": "2028-12-15",
      "dte": 932,
      "strike": 135.0,
      "bid": 51.7,
      "ask": 56.45,
      "mid": 54.075,
      "premium_per_day": 0.05802,
      "delta_from_price": -13.6,
      "open_interest": 60,
      "volume": 3,
      "implied_volatility": 0.707065,
      "iv_vs_hv": 0.9811,
      "in_the_money": false
    }
  ]
}