{
  "fetched_at": "2026-07-13 19:16 UTC",
  "ticker": "MSTR",
  "option_type": "put",
  "strike": 130.0,
  "range": 5.0,
  "current_price": 92.23,
  "hv_context": {
    "currentHV": 0.924971,
    "hvPct": 86,
    "hvMin": 0.445362,
    "hvMax": 1.172094
  },
  "avg_iv": 0.984748,
  "contracts": [
    {
      "option_type": "put",
      "expiration_date": "2026-07-17",
      "dte": 4,
      "strike": 125.0,
      "bid": 32.7,
      "ask": 33.55,
      "mid": 33.125,
      "premium_per_day": 8.28125,
      "delta_from_price": 32.77,
      "open_interest": 1301,
      "volume": 95,
      "implied_volatility": 1.532229,
      "iv_vs_hv": 1.6565,
      "in_the_money": true
    },
    {
      "option_type": "put",
      "expiration_date": "2026-07-17",
      "dte": 4,
      "strike": 126.0,
      "bid": 33.4,
      "ask": 35.0,
      "mid": 34.2,
      "premium_per_day": 8.55,
      "delta_from_price": 33.77,
      "open_interest": 19,
      "volume": 1,
      "implied_volatility": 1.624025,
      "iv_vs_hv": 1.7558,
      "in_the_money": true
    },
    {
      "option_type": "put",
      "expiration_date": "2026-07-17",
      "dte": 4,
      "strike": 127.0,
      "bid": 34.7,
      "ask": 35.85,
      "mid": 35.275,
      "premium_per_day": 8.81875,
      "delta_from_price": 34.77,
      "open_interest": 9,
      "volume": 1,
      "implied_volatility": 1.710939,
      "iv_vs_hv": 1.8497,
      "in_the_money": true
    },
    {
      "option_type": "put",
      "expiration_date": "2026-07-17",
      "dte": 4,
      "strike": 128.0,
      "bid": 35.85,
      "ask": 36.95,
      "mid": 36.4,
      "premium_per_day": 9.1,
      "delta_from_price": 35.77,
      "open_interest": 5,
      "volume": 1,
      "implied_volatility": 1.828126,
      "iv_vs_hv": 1.9764,
      "in_the_money": true
    },
    {
      "option_type": "put",
      "expiration_date": "2026-07-17",
      "dte": 4,
      "strike": 130.0,
      "bid": 37.7,
      "ask": 38.95,
      "mid": 38.325,
      "premium_per_day": 9.58125,
      "delta_from_price": 37.77,
      "open_interest": 3850,
      "volume": 15,
      "implied_volatility": 1.840821,
      "iv_vs_hv": 1.9901,
      "in_the_money": true
    },
    {
      "option_type": "put",
      "expiration_date": "2026-07-24",
      "dte": 11,
      "strike": 125.0,
      "bid": 32.7,
      "ask": 34.15,
      "mid": 33.425,
      "premium_per_day": 3.038636,
      "delta_from_price": 32.77,
      "open_interest": 816,
      "volume": 3,
      "implied_volatility": 1.125981,
      "iv_vs_hv": 1.2173,
      "in_the_money": true
    },
    {
      "option_type": "put",
      "expiration_date": "2026-07-24",
      "dte": 11,
      "strike": 126.0,
      "bid": 33.5,
      "ask": 35.15,
      "mid": 34.325,
      "premium_per_day": 3.120455,
      "delta_from_price": 33.77,
      "open_interest": 22,
      "volume": 3,
      "implied_volatility": 1.10645,
      "iv_vs_hv": 1.1962,
      "in_the_money": true
    },
    {
      "option_type": "put",
      "expiration_date": "2026-07-24",
      "dte": 11,
      "strike": 127.0,
      "bid": 34.7,
      "ask": 36.15,
      "mid": 35.425,
      "premium_per_day": 3.220455,
      "delta_from_price": 34.77,
      "open_interest": 69,
      "volume": 2,
      "implied_volatility": 1.168949,
      "iv_vs_hv": 1.2638,
      "in_the_money": true
    },
    {
      "option_type": "put",
      "expiration_date": "2026-07-24",
      "dte": 11,
      "strike": 128.0,
      "bid": 35.7,
      "ask": 37.1,
      "mid": 36.4,
      "premium_per_day": 3.309091,
      "delta_from_price": 35.77,
      "open_interest": 360,
      "volume": 1,
      "implied_volatility": 1.179692,
      "iv_vs_hv": 1.2754,
      "in_the_money": true
    },
    {
      "option_type": "put",
      "expiration_date": "2026-07-24",
      "dte": 11,
      "strike": 129.0,
      "bid": 36.75,
      "ask": 38.15,
      "mid": 37.45,
      "premium_per_day": 3.404545,
      "delta_from_price": 36.77,
      "open_interest": 593,
      "volume": 2,
      "implied_volatility": 1.221195,
      "iv_vs_hv": 1.3203,
      "in_the_money": true
    },
    {
      "option_type": "put",
      "expiration_date": "2026-07-24",
      "dte": 11,
      "strike": 130.0,
      "bid": 37.75,
      "ask": 38.6,
      "mid": 38.175,
      "premium_per_day": 3.470455,
      "delta_from_price": 37.77,
      "open_interest": 876,
      "volume": 156,
      "implied_volatility": 1.115239,
      "iv_vs_hv": 1.2057,
      "in_the_money": true
    },
    {
      "option_type": "put",
      "expiration_date": "2026-07-24",
      "dte": 11,
      "strike": 131.0,
      "bid": 38.75,
      "ask": 40.05,
      "mid": 39.4,
      "premium_per_day": 3.581818,
      "delta_from_price": 38.77,
      "open_interest": 83,
      "volume": 7,
      "implied_volatility": 1.241215,
      "iv_vs_hv": 1.3419,
      "in_the_money": true
    },
    {
      "option_type": "put",
      "expiration_date": "2026-07-24",
      "dte": 11,
      "strike": 132.0,
      "bid": 39.45,
      "ask": 41.15,
      "mid": 40.3,
      "premium_per_day": 3.663636,
      "delta_from_price": 39.77,
      "open_interest": 9,
      "volume": 1,
      "implied_volatility": 1.216801,
      "iv_vs_hv": 1.3155,
      "in_the_money": true
    },
    {
      "option_type": "put",
      "expiration_date": "2026-07-24",
      "dte": 11,
      "strike": 133.0,
      "bid": 40.45,
      "ask": 42.2,
      "mid": 41.325,
      "premium_per_day": 3.756818,
      "delta_from_price": 40.77,
      "open_interest": 8,
      "volume": 1,
      "implied_volatility": 1.248051,
      "iv_vs_hv": 1.3493,
      "in_the_money": true
    },
    {
      "option_type": "put",
      "expiration_date": "2026-07-24",
      "dte": 11,
      "strike": 134.0,
      "bid": 41.4,
      "ask": 43.15,
      "mid": 42.275,
      "premium_per_day": 3.843182,
      "delta_from_price": 41.77,
      "open_interest": 8,
      "volume": 1,
      "implied_volatility": 1.243168,
      "iv_vs_hv": 1.344,
      "in_the_money": true
    },
    {
      "option_type": "put",
      "expiration_date": "2026-07-24",
      "dte": 11,
      "strike": 135.0,
      "bid": 42.75,
      "ask": 44.0,
      "mid": 43.375,
      "premium_per_day": 3.943182,
      "delta_from_price": 42.77,
      "open_interest": 108,
      "volume": 20,
      "implied_volatility": 1.309574,
      "iv_vs_hv": 1.4158,
      "in_the_money": true
    },
    {
      "option_type": "put",
      "expiration_date": "2026-07-31",
      "dte": 18,
      "strike": 125.0,
      "bid": 33.1,
      "ask": 34.75,
      "mid": 33.925,
      "premium_per_day": 1.884722,
      "delta_from_price": 32.77,
      "open_interest": 457,
      "volume": 1,
      "implied_volatility": 1.029302,
      "iv_vs_hv": 1.1128,
      "in_the_money": true
    },
    {
      "option_type": "put",
      "expiration_date": "2026-07-31",
      "dte": 18,
      "strike": 126.0,
      "bid": 34.15,
      "ask": 35.7,
      "mid": 34.925,
      "premium_per_day": 1.940278,
      "delta_from_price": 33.77,
      "open_interest": 17,
      "volume": 2,
      "implied_volatility": 1.047856,
      "iv_vs_hv": 1.1329,
      "in_the_money": true
    },
    {
      "option_type": "put",
      "expiration_date": "2026-07-31",
      "dte": 18,
      "strike": 127.0,
      "bid": 35.0,
      "ask": 36.65,
      "mid": 35.825,
      "premium_per_day": 1.990278,
      "delta_from_price": 34.77,
      "open_interest": 54,
      "volume": 14,
      "implied_volatility": 1.041509,
      "iv_vs_hv": 1.126,
      "in_the_money": true
    },
    {
      "option_type": "put",
      "expiration_date": "2026-07-31",
      "dte": 18,
      "strike": 128.0,
      "bid": 36.1,
      "ask": 37.6,
      "mid": 36.85,
      "premium_per_day": 2.047222,
      "delta_from_price": 35.77,
      "open_interest": 5,
      "volume": 1,
      "implied_volatility": 1.065923,
      "iv_vs_hv": 1.1524,
      "in_the_money": true
    },
    {
      "option_type": "put",
      "expiration_date": "2026-07-31",
      "dte": 18,
      "strike": 129.0,
      "bid": 36.9,
      "ask": 38.45,
      "mid": 37.675,
      "premium_per_day": 2.093056,
      "delta_from_price": 36.77,
      "open_interest": 26,
      "volume": 1,
      "implied_volatility": 1.037114,
      "iv_vs_hv": 1.1212,
      "in_the_money": true
    },
    {
      "option_type": "put",
      "expiration_date": "2026-07-31",
      "dte": 18,
      "strike": 130.0,
      "bid": 38.0,
      "ask": 39.55,
      "mid": 38.775,
      "premium_per_day": 2.154167,
      "delta_from_price": 37.77,
      "open_interest": 413,
      "volume": 1,
      "implied_volatility": 1.081548,
      "iv_vs_hv": 1.1693,
      "in_the_money": true
    },
    {
      "option_type": "put",
      "expiration_date": "2026-07-31",
      "dte": 18,
      "strike": 131.0,
      "bid": 38.95,
      "ask": 40.5,
      "mid": 39.725,
      "premium_per_day": 2.206944,
      "delta_from_price": 38.77,
      "open_interest": 45,
      "volume": 1,
      "implied_volatility": 1.085454,
      "iv_vs_hv": 1.1735,
      "in_the_money": true
    },
    {
      "option_type": "put",
      "expiration_date": "2026-07-31",
      "dte": 18,
      "strike": 132.0,
      "bid": 39.85,
      "ask": 41.5,
      "mid": 40.675,
      "premium_per_day": 2.259722,
      "delta_from_price": 39.77,
      "open_interest": 4,
      "volume": 1,
      "implied_volatility": 1.087895,
      "iv_vs_hv": 1.1761,
      "in_the_money": true
    },
    {
      "option_type": "put",
      "expiration_date": "2026-07-31",
      "dte": 18,
      "strike": 133.0,
      "bid": 40.8,
      "ask": 42.45,
      "mid": 41.625,
      "premium_per_day": 2.3125,
      "delta_from_price": 40.77,
      "open_interest": 7,
      "volume": 2,
      "implied_volatility": 1.089848,
      "iv_vs_hv": 1.1783,
      "in_the_money": true
    },
    {
      "option_type": "put",
      "expiration_date": "2026-07-31",
      "dte": 18,
      "strike": 134.0,
      "bid": 41.8,
      "ask": 43.45,
      "mid": 42.625,
      "premium_per_day": 2.368056,
      "delta_from_price": 41.77,
      "open_interest": 11,
      "volume": 7,
      "implied_volatility": 1.10645,
      "iv_vs_hv": 1.1962,
      "in_the_money": true
    },
    {
      "option_type": "put",
      "expiration_date": "2026-07-31",
      "dte": 18,
      "strike": 135.0,
      "bid": 42.85,
      "ask": 44.4,
      "mid": 43.625,
      "premium_per_day": 2.423611,
      "delta_from_price": 42.77,
      "open_interest": 441,
      "volume": 3,
      "implied_volatility": 1.122075,
      "iv_vs_hv": 1.2131,
      "in_the_money": true
    },
    {
      "option_type": "put",
      "expiration_date": "2026-08-07",
      "dte": 25,
      "strike": 125.0,
      "bid": 33.65,
      "ask": 35.35,
      "mid": 34.5,
      "premium_per_day": 1.38,
      "delta_from_price": 32.77,
      "open_interest": 121,
      "volume": 3,
      "implied_volatility": 0.986817,
      "iv_vs_hv": 1.0669,
      "in_the_money": true
    },
    {
      "option_type": "put",
      "expiration_date": "2026-08-07",
      "dte": 25,
      "strike": 130.0,
      "bid": 38.25,
      "ask": 40.05,
      "mid": 39.15,
      "premium_per_day": 1.566,
      "delta_from_price": 37.77,
      "open_interest": 148,
      "volume": 3,
      "implied_volatility": 1.003911,
      "iv_vs_hv": 1.0853,
      "in_the_money": true
    },
    {
      "option_type": "put",
      "expiration_date": "2026-08-07",
      "dte": 25,
      "strike": 135.0,
      "bid": 43.05,
      "ask": 44.4,
      "mid": 43.725,
      "premium_per_day": 1.749,
      "delta_from_price": 42.77,
      "open_interest": 43,
      "volume": 1,
      "implied_volatility": 0.984375,
      "iv_vs_hv": 1.0642,
      "in_the_money": true
    },
    {
      "option_type": "put",
      "expiration_date": "2026-08-14",
      "dte": 32,
      "strike": 125.0,
      "bid": 34.0,
      "ask": 35.85,
      "mid": 34.925,
      "premium_per_day": 1.091406,
      "delta_from_price": 32.77,
      "open_interest": 103,
      "volume": 1,
      "implied_volatility": 0.937989,
      "iv_vs_hv": 1.0141,
      "in_the_money": true
    },
    {
      "option_type": "put",
      "expiration_date": "2026-08-14",
      "dte": 32,
      "strike": 130.0,
      "bid": 38.7,
      "ask": 40.05,
      "mid": 39.375,
      "premium_per_day": 1.230469,
      "delta_from_price": 37.77,
      "open_interest": 52,
      "volume": 43,
      "implied_volatility": 0.928956,
      "iv_vs_hv": 1.0043,
      "in_the_money": true
    },
    {
      "option_type": "put",
      "expiration_date": "2026-08-21",
      "dte": 39,
      "strike": 125.0,
      "bid": 34.6,
      "ask": 35.8,
      "mid": 35.2,
      "premium_per_day": 0.902564,
      "delta_from_price": 32.77,
      "open_interest": 1976,
      "volume": 15,
      "implied_volatility": 0.886232,
      "iv_vs_hv": 0.9581,
      "in_the_money": true
    },
    {
      "option_type": "put",
      "expiration_date": "2026-08-21",
      "dte": 39,
      "strike": 130.0,
      "bid": 39.1,
      "ask": 40.5,
      "mid": 39.8,
      "premium_per_day": 1.020513,
      "delta_from_price": 37.77,
      "open_interest": 7400,
      "volume": 77,
      "implied_volatility": 0.90381,
      "iv_vs_hv": 0.9771,
      "in_the_money": true
    },
    {
      "option_type": "put",
      "expiration_date": "2026-08-21",
      "dte": 39,
      "strike": 135.0,
      "bid": 43.75,
      "ask": 45.15,
      "mid": 44.45,
      "premium_per_day": 1.139744,
      "delta_from_price": 42.77,
      "open_interest": 1529,
      "volume": 14,
      "implied_volatility": 0.916993,
      "iv_vs_hv": 0.9914,
      "in_the_money": true
    },
    {
      "option_type": "put",
      "expiration_date": "2026-08-28",
      "dte": 46,
      "strike": 130.0,
      "bid": 38.55,
      "ask": 41.45,
      "mid": 40.0,
      "premium_per_day": 0.869565,
      "delta_from_price": 37.77,
      "open_interest": 1,
      "volume": 33,
      "implied_volatility": 0.8584,
      "iv_vs_hv": 0.928,
      "in_the_money": true
    },
    {
      "option_type": "put",
      "expiration_date": "2026-09-18",
      "dte": 67,
      "strike": 125.0,
      "bid": 36.75,
      "ask": 37.7,
      "mid": 37.225,
      "premium_per_day": 0.555597,
      "delta_from_price": 32.77,
      "open_interest": 1172,
      "volume": 29,
      "implied_volatility": 0.850099,
      "iv_vs_hv": 0.9191,
      "in_the_money": true
    },
    {
      "option_type": "put",
      "expiration_date": "2026-09-18",
      "dte": 67,
      "strike": 130.0,
      "bid": 41.05,
      "ask": 42.35,
      "mid": 41.7,
      "premium_per_day": 0.622388,
      "delta_from_price": 37.77,
      "open_interest": 1341,
      "volume": 54,
      "implied_volatility": 0.865968,
      "iv_vs_hv": 0.9362,
      "in_the_money": true
    },
    {
      "option_type": "put",
      "expiration_date": "2026-09-18",
      "dte": 67,
      "strike": 135.0,
      "bid": 44.9,
      "ask": 46.95,
      "mid": 45.925,
      "premium_per_day": 0.685448,
      "delta_from_price": 42.77,
      "open_interest": 951,
      "volume": 6,
      "implied_volatility": 0.852052,
      "iv_vs_hv": 0.9212,
      "in_the_money": true
    },
    {
      "option_type": "put",
      "expiration_date": "2026-10-16",
      "dte": 95,
      "strike": 125.0,
      "bid": 38.6,
      "ask": 39.9,
      "mid": 39.25,
      "premium_per_day": 0.413158,
      "delta_from_price": 32.77,
      "open_interest": 892,
      "volume": 1,
      "implied_volatility": 0.841432,
      "iv_vs_hv": 0.9097,
      "in_the_money": true
    },
    {
      "option_type": "put",
      "expiration_date": "2026-10-16",
      "dte": 95,
      "strike": 130.0,
      "bid": 42.75,
      "ask": 44.05,
      "mid": 43.4,
      "premium_per_day": 0.456842,
      "delta_from_price": 37.77,
      "open_interest": 873,
      "volume": 26,
      "implied_volatility": 0.840456,
      "iv_vs_hv": 0.9086,
      "in_the_money": true
    },
    {
      "option_type": "put",
      "expiration_date": "2026-10-16",
      "dte": 95,
      "strike": 135.0,
      "bid": 46.85,
      "ask": 48.25,
      "mid": 47.55,
      "premium_per_day": 0.500526,
      "delta_from_price": 42.77,
      "open_interest": 1006,
      "volume": 21,
      "implied_volatility": 0.832399,
      "iv_vs_hv": 0.8999,
      "in_the_money": true
    },
    {
      "option_type": "put",
      "expiration_date": "2026-11-20",
      "dte": 130,
      "strike": 125.0,
      "bid": 40.95,
      "ask": 42.35,
      "mid": 41.65,
      "premium_per_day": 0.320385,
      "delta_from_price": 32.77,
      "open_interest": 466,
      "volume": 1,
      "implied_volatility": 0.839235,
      "iv_vs_hv": 0.9073,
      "in_the_money": true
    },
    {
      "option_type": "put",
      "expiration_date": "2026-11-20",
      "dte": 130,
      "strike": 130.0,
      "bid": 45.0,
      "ask": 46.35,
      "mid": 45.675,
      "premium_per_day": 0.351346,
      "delta_from_price": 37.77,
      "open_interest": 424,
      "volume": 4,
      "implied_volatility": 0.836794,
      "iv_vs_hv": 0.9047,
      "in_the_money": true
    },
    {
      "option_type": "put",
      "expiration_date": "2026-11-20",
      "dte": 130,
      "strike": 135.0,
      "bid": 49.1,
      "ask": 50.45,
      "mid": 49.775,
      "premium_per_day": 0.382885,
      "delta_from_price": 42.77,
      "open_interest": 137,
      "volume": 2,
      "implied_volatility": 0.833009,
      "iv_vs_hv": 0.9006,
      "in_the_money": true
    },
    {
      "option_type": "put",
      "expiration_date": "2026-12-18",
      "dte": 158,
      "strike": 125.0,
      "bid": 42.5,
      "ask": 43.8,
      "mid": 43.15,
      "premium_per_day": 0.273101,
      "delta_from_price": 32.77,
      "open_interest": 1040,
      "volume": 3,
      "implied_volatility": 0.826784,
      "iv_vs_hv": 0.8938,
      "in_the_money": true
    },
    {
      "option_type": "put",
      "expiration_date": "2026-12-18",
      "dte": 158,
      "strike": 130.0,
      "bid": 46.45,
      "ask": 47.8,
      "mid": 47.125,
      "premium_per_day": 0.298259,
      "delta_from_price": 37.77,
      "open_interest": 2607,
      "volume": 1,
      "implied_volatility": 0.824221,
      "iv_vs_hv": 0.8911,
      "in_the_money": true
    },
    {
      "option_type": "put",
      "expiration_date": "2026-12-18",
      "dte": 158,
      "strike": 135.0,
      "bid": 50.55,
      "ask": 51.9,
      "mid": 51.225,
      "premium_per_day": 0.324209,
      "delta_from_price": 42.77,
      "open_interest": 771,
      "volume": 2,
      "implied_volatility": 0.822878,
      "iv_vs_hv": 0.8896,
      "in_the_money": true
    },
    {
      "option_type": "put",
      "expiration_date": "2027-01-15",
      "dte": 186,
      "strike": 125.0,
      "bid": 43.75,
      "ask": 45.25,
      "mid": 44.5,
      "premium_per_day": 0.239247,
      "delta_from_price": 32.77,
      "open_interest": 1037,
      "volume": 9,
      "implied_volatility": 0.81537,
      "iv_vs_hv": 0.8815,
      "in_the_money": true
    },
    {
      "option_type": "put",
      "expiration_date": "2027-01-15",
      "dte": 186,
      "strike": 130.0,
      "bid": 47.7,
      "ask": 49.2,
      "mid": 48.45,
      "premium_per_day": 0.260484,
      "delta_from_price": 37.77,
      "open_interest": 1286,
      "volume": 1,
      "implied_volatility": 0.813112,
      "iv_vs_hv": 0.8791,
      "in_the_money": true
    },
    {
      "option_type": "put",
      "expiration_date": "2027-01-15",
      "dte": 186,
      "strike": 135.0,
      "bid": 51.7,
      "ask": 53.5,
      "mid": 52.6,
      "premium_per_day": 0.282796,
      "delta_from_price": 42.77,
      "open_interest": 1080,
      "volume": 1,
      "implied_volatility": 0.815309,
      "iv_vs_hv": 0.8814,
      "in_the_money": true
    },
    {
      "option_type": "put",
      "expiration_date": "2027-03-19",
      "dte": 249,
      "strike": 125.0,
      "bid": 46.85,
      "ask": 48.7,
      "mid": 47.775,
      "premium_per_day": 0.191867,
      "delta_from_price": 32.77,
      "open_interest": 345,
      "volume": 1,
      "implied_volatility": 0.814455,
      "iv_vs_hv": 0.8805,
      "in_the_money": true
    },
    {
      "option_type": "put",
      "expiration_date": "2027-03-19",
      "dte": 249,
      "strike": 130.0,
      "bid": 50.65,
      "ask": 52.5,
      "mid": 51.575,
      "premium_per_day": 0.207129,
      "delta_from_price": 37.77,
      "open_interest": 381,
      "volume": 2,
      "implied_volatility": 0.808901,
      "iv_vs_hv": 0.8745,
      "in_the_money": true
    },
    {
      "option_type": "put",
      "expiration_date": "2027-03-19",
      "dte": 249,
      "strike": 135.0,
      "bid": 54.2,
      "ask": 56.45,
      "mid": 55.325,
      "premium_per_day": 0.222189,
      "delta_from_price": 42.77,
      "open_interest": 132,
      "volume": 1,
      "implied_volatility": 0.798891,
      "iv_vs_hv": 0.8637,
      "in_the_money": true
    },
    {
      "option_type": "put",
      "expiration_date": "2027-06-17",
      "dte": 339,
      "strike": 125.0,
      "bid": 50.4,
      "ask": 52.5,
      "mid": 51.45,
      "premium_per_day": 0.15177,
      "delta_from_price": 32.77,
      "open_interest": 1005,
      "volume": 1,
      "implied_volatility": 0.802004,
      "iv_vs_hv": 0.8671,
      "in_the_money": true
    },
    {
      "option_type": "put",
      "expiration_date": "2027-06-17",
      "dte": 339,
      "strike": 130.0,
      "bid": 54.25,
      "ask": 56.4,
      "mid": 55.325,
      "premium_per_day": 0.163201,
      "delta_from_price": 37.77,
      "open_interest": 340,
      "volume": 4,
      "implied_volatility": 0.799929,
      "iv_vs_hv": 0.8648,
      "in_the_money": true
    },
    {
      "option_type": "put",
      "expiration_date": "2027-06-17",
      "dte": 339,
      "strike": 135.0,
      "bid": 58.15,
      "ask": 60.3,
      "mid": 59.225,
      "premium_per_day": 0.174705,
      "delta_from_price": 42.77,
      "open_interest": 360,
      "volume": 3,
      "implied_volatility": 0.796572,
      "iv_vs_hv": 0.8612,
      "in_the_money": true
    },
    {
      "option_type": "put",
      "expiration_date": "2027-09-17",
      "dte": 431,
      "strike": 125.0,
      "bid": 52.95,
      "ask": 56.2,
      "mid": 54.575,
      "premium_per_day": 0.126624,
      "delta_from_price": 32.77,
      "open_interest": 452,
      "volume": 2,
      "implied_volatility": 0.789705,
      "iv_vs_hv": 0.8538,
      "in_the_money": true
    },
    {
      "option_type": "put",
      "expiration_date": "2027-09-17",
      "dte": 431,
      "strike": 130.0,
      "bid": 57.1,
      "ask": 59.75,
      "mid": 58.425,
      "premium_per_day": 0.135557,
      "delta_from_price": 37.77,
      "open_interest": 614,
      "volume": 1,
      "implied_volatility": 0.787234,
      "iv_vs_hv": 0.8511,
      "in_the_money": true
    },
    {
      "option_type": "put",
      "expiration_date": "2027-09-17",
      "dte": 431,
      "strike": 135.0,
      "bid": 59.85,
      "ask": 63.7,
      "mid": 61.775,
      "premium_per_day": 0.143329,
      "delta_from_price": 42.77,
      "open_interest": 220,
      "volume": 32,
      "implied_volatility": 0.770632,
      "iv_vs_hv": 0.8331,
      "in_the_money": true
    },
    {
      "option_type": "put",
      "expiration_date": "2027-12-17",
      "dte": 522,
      "strike": 125.0,
      "bid": 56.15,
      "ask": 60.6,
      "mid": 58.375,
      "premium_per_day": 0.11183,
      "delta_from_price": 32.77,
      "open_interest": 691,
      "volume": 5,
      "implied_volatility": 0.80475,
      "iv_vs_hv": 0.87,
      "in_the_money": true
    },
    {
      "option_type": "put",
      "expiration_date": "2027-12-17",
      "dte": 522,
      "strike": 130.0,
      "bid": 59.5,
      "ask": 63.85,
      "mid": 61.675,
      "premium_per_day": 0.118151,
      "delta_from_price": 37.77,
      "open_interest": 362,
      "volume": 3,
      "implied_volatility": 0.789522,
      "iv_vs_hv": 0.8536,
      "in_the_money": true
    },
    {
      "option_type": "put",
      "expiration_date": "2027-12-17",
      "dte": 522,
      "strike": 135.0,
      "bid": 62.25,
      "ask": 68.05,
      "mid": 65.15,
      "premium_per_day": 0.124808,
      "delta_from_price": 42.77,
      "open_interest": 383,
      "volume": 43,
      "implied_volatility": 0.777132,
      "iv_vs_hv": 0.8402,
      "in_the_money": true
    },
    {
      "option_type": "put",
      "expiration_date": "2028-01-21",
      "dte": 557,
      "strike": 125.0,
      "bid": 57.0,
      "ask": 60.1,
      "mid": 58.55,
      "premium_per_day": 0.105117,
      "delta_from_price": 32.77,
      "open_interest": 125,
      "volume": 1,
      "implied_volatility": 0.783022,
      "iv_vs_hv": 0.8465,
      "in_the_money": true
    },
    {
      "option_type": "put",
      "expiration_date": "2028-01-21",
      "dte": 557,
      "strike": 130.0,
      "bid": 60.85,
      "ask": 64.7,
      "mid": 62.775,
      "premium_per_day": 0.112702,
      "delta_from_price": 37.77,
      "open_interest": 460,
      "volume": 5,
      "implied_volatility": 0.788759,
      "iv_vs_hv": 0.8527,
      "in_the_money": true
    },
    {
      "option_type": "put",
      "expiration_date": "2028-01-21",
      "dte": 557,
      "strike": 135.0,
      "bid": 64.05,
      "ask": 68.65,
      "mid": 66.35,
      "premium_per_day": 0.11912,
      "delta_from_price": 42.77,
      "open_interest": 499,
      "volume": 1,
      "implied_volatility": 0.778841,
      "iv_vs_hv": 0.842,
      "in_the_money": true
    },
    {
      "option_type": "put",
      "expiration_date": "2028-06-16",
      "dte": 704,
      "strike": 125.0,
      "bid": 58.5,
      "ask": 65.3,
      "mid": 61.9,
      "premium_per_day": 0.087926,
      "delta_from_price": 32.77,
      "open_interest": 340,
      "volume": 1,
      "implied_volatility": 0.763644,
      "iv_vs_hv": 0.8256,
      "in_the_money": true
    },
    {
      "option_type": "put",
      "expiration_date": "2028-06-16",
      "dte": 704,
      "strike": 130.0,
      "bid": 62.0,
      "ask": 71.0,
      "mid": 66.5,
      "premium_per_day": 0.09446,
      "delta_from_price": 37.77,
      "open_interest": 112,
      "volume": 1,
      "implied_volatility": 0.775851,
      "iv_vs_hv": 0.8388,
      "in_the_money": true
    },
    {
      "option_type": "put",
      "expiration_date": "2028-06-16",
      "dte": 704,
      "strike": 135.0,
      "bid": 66.0,
      "ask": 73.3,
      "mid": 69.65,
      "premium_per_day": 0.098935,
      "delta_from_price": 42.77,
      "open_interest": 334,
      "volume": 1,
      "implied_volatility": 0.758059,
      "iv_vs_hv": 0.8195,
      "in_the_money": true
    },
    {
      "option_type": "put",
      "expiration_date": "2028-12-15",
      "dte": 886,
      "strike": 125.0,
      "bid": 64.45,
      "ask": 70.1,
      "mid": 67.275,
      "premium_per_day": 0.075931,
      "delta_from_price": 32.77,
      "open_interest": 110,
      "volume": 13,
      "implied_volatility": 0.779024,
      "iv_vs_hv": 0.8422,
      "in_the_money": true
    },
    {
      "option_type": "put",
      "expiration_date": "2028-12-15",
      "dte": 886,
      "strike": 130.0,
      "bid": 68.8,
      "ask": 72.8,
      "mid": 70.8,
      "premium_per_day": 0.07991,
      "delta_from_price": 37.77,
      "open_interest": 194,
      "volume": 2,
      "implied_volatility": 0.769534,
      "iv_vs_hv": 0.832,
      "in_the_money": true
    },
    {
      "option_type": "put",
      "expiration_date": "2028-12-15",
      "dte": 886,
      "strike": 135.0,
      "bid": 70.8,
      "ask": 75.85,
      "mid": 73.325,
      "premium_per_day": 0.08276,
      "delta_from_price": 42.77,
      "open_interest": 336,
      "volume": 1,
      "implied_volatility": 0.741397,
      "iv_vs_hv": 0.8015,
      "in_the_money": true
    }
  ]
}