{
  "fetched_at": "2026-04-23 15:09 UTC",
  "ticker": "MSTR",
  "option_type": "put",
  "strike": 130.0,
  "range": 5.0,
  "current_price": 178.96,
  "hv_context": {
    "currentHV": 0.659954,
    "hvPct": 67,
    "hvMin": 0.413902,
    "hvMax": 1.172094
  },
  "avg_iv": 0.954042,
  "contracts": [
    {
      "option_type": "put",
      "expiration_date": "2026-04-24",
      "dte": 1,
      "strike": 125.0,
      "bid": 0.01,
      "ask": 0.06,
      "mid": 0.035,
      "premium_per_day": 0.035,
      "delta_from_price": -53.96,
      "open_interest": 2843,
      "volume": 38,
      "implied_volatility": 1.890626,
      "iv_vs_hv": 2.8648,
      "in_the_money": false
    },
    {
      "option_type": "put",
      "expiration_date": "2026-04-24",
      "dte": 1,
      "strike": 126.0,
      "bid": 0.0,
      "ask": 0.23,
      "mid": 0.115,
      "premium_per_day": 0.115,
      "delta_from_price": -52.96,
      "open_interest": 879,
      "volume": 10,
      "implied_volatility": 2.148442,
      "iv_vs_hv": 3.2554,
      "in_the_money": false
    },
    {
      "option_type": "put",
      "expiration_date": "2026-04-24",
      "dte": 1,
      "strike": 127.0,
      "bid": 0.02,
      "ask": 0.1,
      "mid": 0.06,
      "premium_per_day": 0.06,
      "delta_from_price": -51.96,
      "open_interest": 425,
      "volume": 11,
      "implied_volatility": 1.9375,
      "iv_vs_hv": 2.9358,
      "in_the_money": false
    },
    {
      "option_type": "put",
      "expiration_date": "2026-04-24",
      "dte": 1,
      "strike": 128.0,
      "bid": 0.01,
      "ask": 0.07,
      "mid": 0.04,
      "premium_per_day": 0.04,
      "delta_from_price": -50.96,
      "open_interest": 2440,
      "volume": 12,
      "implied_volatility": 1.812501,
      "iv_vs_hv": 2.7464,
      "in_the_money": false
    },
    {
      "option_type": "put",
      "expiration_date": "2026-04-24",
      "dte": 1,
      "strike": 129.0,
      "bid": 0.0,
      "ask": 0.15,
      "mid": 0.075,
      "premium_per_day": 0.075,
      "delta_from_price": -49.96,
      "open_interest": 528,
      "volume": 1,
      "implied_volatility": 1.910157,
      "iv_vs_hv": 2.8944,
      "in_the_money": false
    },
    {
      "option_type": "put",
      "expiration_date": "2026-04-24",
      "dte": 1,
      "strike": 130.0,
      "bid": 0.02,
      "ask": 0.05,
      "mid": 0.035,
      "premium_per_day": 0.035,
      "delta_from_price": -48.96,
      "open_interest": 4818,
      "volume": 102,
      "implied_volatility": 1.703126,
      "iv_vs_hv": 2.5807,
      "in_the_money": false
    },
    {
      "option_type": "put",
      "expiration_date": "2026-04-24",
      "dte": 1,
      "strike": 131.0,
      "bid": 0.0,
      "ask": 0.51,
      "mid": 0.255,
      "premium_per_day": 0.255,
      "delta_from_price": -47.96,
      "open_interest": 798,
      "volume": 7,
      "implied_volatility": 2.187505,
      "iv_vs_hv": 3.3146,
      "in_the_money": false
    },
    {
      "option_type": "put",
      "expiration_date": "2026-04-24",
      "dte": 1,
      "strike": 132.0,
      "bid": 0.0,
      "ask": 0.51,
      "mid": 0.255,
      "premium_per_day": 0.255,
      "delta_from_price": -46.96,
      "open_interest": 857,
      "volume": 50,
      "implied_volatility": 2.142583,
      "iv_vs_hv": 3.2466,
      "in_the_money": false
    },
    {
      "option_type": "put",
      "expiration_date": "2026-04-24",
      "dte": 1,
      "strike": 133.0,
      "bid": 0.0,
      "ask": 0.16,
      "mid": 0.08,
      "premium_per_day": 0.08,
      "delta_from_price": -45.96,
      "open_interest": 2728,
      "volume": 1210,
      "implied_volatility": 1.765626,
      "iv_vs_hv": 2.6754,
      "in_the_money": false
    },
    {
      "option_type": "put",
      "expiration_date": "2026-04-24",
      "dte": 1,
      "strike": 134.0,
      "bid": 0.0,
      "ask": 0.51,
      "mid": 0.255,
      "premium_per_day": 0.255,
      "delta_from_price": -44.96,
      "open_interest": 977,
      "volume": 12,
      "implied_volatility": 2.050786,
      "iv_vs_hv": 3.1075,
      "in_the_money": false
    },
    {
      "option_type": "put",
      "expiration_date": "2026-04-24",
      "dte": 1,
      "strike": 135.0,
      "bid": 0.03,
      "ask": 0.1,
      "mid": 0.065,
      "premium_per_day": 0.065,
      "delta_from_price": -43.96,
      "open_interest": 2136,
      "volume": 46,
      "implied_volatility": 1.640627,
      "iv_vs_hv": 2.486,
      "in_the_money": false
    },
    {
      "option_type": "put",
      "expiration_date": "2026-05-01",
      "dte": 8,
      "strike": 125.0,
      "bid": 0.19,
      "ask": 0.23,
      "mid": 0.21,
      "premium_per_day": 0.02625,
      "delta_from_price": -53.96,
      "open_interest": 2541,
      "volume": 63,
      "implied_volatility": 1.128911,
      "iv_vs_hv": 1.7106,
      "in_the_money": false
    },
    {
      "option_type": "put",
      "expiration_date": "2026-05-01",
      "dte": 8,
      "strike": 126.0,
      "bid": 0.15,
      "ask": 0.3,
      "mid": 0.225,
      "premium_per_day": 0.028125,
      "delta_from_price": -52.96,
      "open_interest": 316,
      "volume": 1,
      "implied_volatility": 1.119145,
      "iv_vs_hv": 1.6958,
      "in_the_money": false
    },
    {
      "option_type": "put",
      "expiration_date": "2026-05-01",
      "dte": 8,
      "strike": 127.0,
      "bid": 0.16,
      "ask": 0.27,
      "mid": 0.215,
      "premium_per_day": 0.026875,
      "delta_from_price": -51.96,
      "open_interest": 171,
      "volume": 4,
      "implied_volatility": 1.089848,
      "iv_vs_hv": 1.6514,
      "in_the_money": false
    },
    {
      "option_type": "put",
      "expiration_date": "2026-05-01",
      "dte": 8,
      "strike": 128.0,
      "bid": 0.19,
      "ask": 0.3,
      "mid": 0.245,
      "premium_per_day": 0.030625,
      "delta_from_price": -50.96,
      "open_interest": 141,
      "volume": 15,
      "implied_volatility": 1.089848,
      "iv_vs_hv": 1.6514,
      "in_the_money": false
    },
    {
      "option_type": "put",
      "expiration_date": "2026-05-01",
      "dte": 8,
      "strike": 129.0,
      "bid": 0.2,
      "ask": 0.37,
      "mid": 0.285,
      "premium_per_day": 0.035625,
      "delta_from_price": -49.96,
      "open_interest": 56,
      "volume": 13,
      "implied_volatility": 1.095708,
      "iv_vs_hv": 1.6603,
      "in_the_money": false
    },
    {
      "option_type": "put",
      "expiration_date": "2026-05-01",
      "dte": 8,
      "strike": 130.0,
      "bid": 0.21,
      "ask": 0.27,
      "mid": 0.24,
      "premium_per_day": 0.03,
      "delta_from_price": -48.96,
      "open_interest": 2438,
      "volume": 105,
      "implied_volatility": 1.042974,
      "iv_vs_hv": 1.5804,
      "in_the_money": false
    },
    {
      "option_type": "put",
      "expiration_date": "2026-05-01",
      "dte": 8,
      "strike": 131.0,
      "bid": 0.18,
      "ask": 0.36,
      "mid": 0.27,
      "premium_per_day": 0.03375,
      "delta_from_price": -47.96,
      "open_interest": 269,
      "volume": 2,
      "implied_volatility": 1.04102,
      "iv_vs_hv": 1.5774,
      "in_the_money": false
    },
    {
      "option_type": "put",
      "expiration_date": "2026-05-01",
      "dte": 8,
      "strike": 132.0,
      "bid": 0.16,
      "ask": 0.46,
      "mid": 0.31,
      "premium_per_day": 0.03875,
      "delta_from_price": -46.96,
      "open_interest": 208,
      "volume": 140,
      "implied_volatility": 1.04395,
      "iv_vs_hv": 1.5819,
      "in_the_money": false
    },
    {
      "option_type": "put",
      "expiration_date": "2026-05-01",
      "dte": 8,
      "strike": 133.0,
      "bid": 0.19,
      "ask": 0.41,
      "mid": 0.3,
      "premium_per_day": 0.0375,
      "delta_from_price": -45.96,
      "open_interest": 198,
      "volume": 2,
      "implied_volatility": 1.01563,
      "iv_vs_hv": 1.5389,
      "in_the_money": false
    },
    {
      "option_type": "put",
      "expiration_date": "2026-05-01",
      "dte": 8,
      "strike": 134.0,
      "bid": 0.22,
      "ask": 0.41,
      "mid": 0.315,
      "premium_per_day": 0.039375,
      "delta_from_price": -44.96,
      "open_interest": 54,
      "volume": 5,
      "implied_volatility": 1.002935,
      "iv_vs_hv": 1.5197,
      "in_the_money": false
    },
    {
      "option_type": "put",
      "expiration_date": "2026-05-01",
      "dte": 8,
      "strike": 135.0,
      "bid": 0.26,
      "ask": 0.3,
      "mid": 0.28,
      "premium_per_day": 0.035,
      "delta_from_price": -43.96,
      "open_interest": 2076,
      "volume": 82,
      "implied_volatility": 0.960938,
      "iv_vs_hv": 1.4561,
      "in_the_money": false
    },
    {
      "option_type": "put",
      "expiration_date": "2026-05-08",
      "dte": 15,
      "strike": 125.0,
      "bid": 0.52,
      "ask": 0.65,
      "mid": 0.585,
      "premium_per_day": 0.039,
      "delta_from_price": -53.96,
      "open_interest": 1477,
      "volume": 33,
      "implied_volatility": 1.011724,
      "iv_vs_hv": 1.533,
      "in_the_money": false
    },
    {
      "option_type": "put",
      "expiration_date": "2026-05-08",
      "dte": 15,
      "strike": 126.0,
      "bid": 0.51,
      "ask": 0.8,
      "mid": 0.655,
      "premium_per_day": 0.043667,
      "delta_from_price": -52.96,
      "open_interest": 129,
      "volume": 3,
      "implied_volatility": 1.01563,
      "iv_vs_hv": 1.5389,
      "in_the_money": false
    },
    {
      "option_type": "put",
      "expiration_date": "2026-05-08",
      "dte": 15,
      "strike": 127.0,
      "bid": 0.48,
      "ask": 1.11,
      "mid": 0.795,
      "premium_per_day": 0.053,
      "delta_from_price": -51.96,
      "open_interest": 177,
      "volume": 5,
      "implied_volatility": 1.037602,
      "iv_vs_hv": 1.5722,
      "in_the_money": false
    },
    {
      "option_type": "put",
      "expiration_date": "2026-05-08",
      "dte": 15,
      "strike": 128.0,
      "bid": 0.5,
      "ask": 0.87,
      "mid": 0.685,
      "premium_per_day": 0.045667,
      "delta_from_price": -50.96,
      "open_interest": 348,
      "volume": 1,
      "implied_volatility": 0.986328,
      "iv_vs_hv": 1.4945,
      "in_the_money": false
    },
    {
      "option_type": "put",
      "expiration_date": "2026-05-08",
      "dte": 15,
      "strike": 129.0,
      "bid": 0.57,
      "ask": 0.84,
      "mid": 0.705,
      "premium_per_day": 0.047,
      "delta_from_price": -49.96,
      "open_interest": 25,
      "volume": 2,
      "implied_volatility": 0.973145,
      "iv_vs_hv": 1.4746,
      "in_the_money": false
    },
    {
      "option_type": "put",
      "expiration_date": "2026-05-08",
      "dte": 15,
      "strike": 130.0,
      "bid": 0.71,
      "ask": 0.77,
      "mid": 0.74,
      "premium_per_day": 0.049333,
      "delta_from_price": -48.96,
      "open_interest": 1214,
      "volume": 20,
      "implied_volatility": 0.963868,
      "iv_vs_hv": 1.4605,
      "in_the_money": false
    },
    {
      "option_type": "put",
      "expiration_date": "2026-05-08",
      "dte": 15,
      "strike": 131.0,
      "bid": 0.67,
      "ask": 0.96,
      "mid": 0.815,
      "premium_per_day": 0.054333,
      "delta_from_price": -47.96,
      "open_interest": 17,
      "volume": 3,
      "implied_volatility": 0.964844,
      "iv_vs_hv": 1.462,
      "in_the_money": false
    },
    {
      "option_type": "put",
      "expiration_date": "2026-05-08",
      "dte": 15,
      "strike": 132.0,
      "bid": 0.7,
      "ask": 0.86,
      "mid": 0.78,
      "premium_per_day": 0.052,
      "delta_from_price": -46.96,
      "open_interest": 489,
      "volume": 2,
      "implied_volatility": 0.936524,
      "iv_vs_hv": 1.4191,
      "in_the_money": false
    },
    {
      "option_type": "put",
      "expiration_date": "2026-05-08",
      "dte": 15,
      "strike": 133.0,
      "bid": 0.73,
      "ask": 0.95,
      "mid": 0.84,
      "premium_per_day": 0.056,
      "delta_from_price": -45.96,
      "open_interest": 19,
      "volume": 13,
      "implied_volatility": 0.932618,
      "iv_vs_hv": 1.4132,
      "in_the_money": false
    },
    {
      "option_type": "put",
      "expiration_date": "2026-05-08",
      "dte": 15,
      "strike": 134.0,
      "bid": 0.77,
      "ask": 0.99,
      "mid": 0.88,
      "premium_per_day": 0.058667,
      "delta_from_price": -44.96,
      "open_interest": 114,
      "volume": 1,
      "implied_volatility": 0.923341,
      "iv_vs_hv": 1.3991,
      "in_the_money": false
    },
    {
      "option_type": "put",
      "expiration_date": "2026-05-08",
      "dte": 15,
      "strike": 135.0,
      "bid": 0.81,
      "ask": 0.92,
      "mid": 0.865,
      "premium_per_day": 0.057667,
      "delta_from_price": -43.96,
      "open_interest": 1271,
      "volume": 15,
      "implied_volatility": 0.900392,
      "iv_vs_hv": 1.3643,
      "in_the_money": false
    },
    {
      "option_type": "put",
      "expiration_date": "2026-05-15",
      "dte": 22,
      "strike": 125.0,
      "bid": 0.82,
      "ask": 0.94,
      "mid": 0.88,
      "premium_per_day": 0.04,
      "delta_from_price": -53.96,
      "open_interest": 2960,
      "volume": 75,
      "implied_volatility": 0.91797,
      "iv_vs_hv": 1.391,
      "in_the_money": false
    },
    {
      "option_type": "put",
      "expiration_date": "2026-05-15",
      "dte": 22,
      "strike": 130.0,
      "bid": 1.05,
      "ask": 1.14,
      "mid": 1.095,
      "premium_per_day": 0.049773,
      "delta_from_price": -48.96,
      "open_interest": 3966,
      "volume": 87,
      "implied_volatility": 0.877687,
      "iv_vs_hv": 1.3299,
      "in_the_money": false
    },
    {
      "option_type": "put",
      "expiration_date": "2026-05-15",
      "dte": 22,
      "strike": 135.0,
      "bid": 1.33,
      "ask": 1.39,
      "mid": 1.36,
      "premium_per_day": 0.061818,
      "delta_from_price": -43.96,
      "open_interest": 3391,
      "volume": 84,
      "implied_volatility": 0.838136,
      "iv_vs_hv": 1.27,
      "in_the_money": false
    },
    {
      "option_type": "put",
      "expiration_date": "2026-05-22",
      "dte": 29,
      "strike": 125.0,
      "bid": 1.42,
      "ask": 1.58,
      "mid": 1.5,
      "premium_per_day": 0.051724,
      "delta_from_price": -53.96,
      "open_interest": 951,
      "volume": 19,
      "implied_volatility": 0.910157,
      "iv_vs_hv": 1.3791,
      "in_the_money": false
    },
    {
      "option_type": "put",
      "expiration_date": "2026-05-22",
      "dte": 29,
      "strike": 126.0,
      "bid": 1.25,
      "ask": 2.01,
      "mid": 1.63,
      "premium_per_day": 0.056207,
      "delta_from_price": -52.96,
      "open_interest": 8,
      "volume": 2,
      "implied_volatility": 0.913087,
      "iv_vs_hv": 1.3836,
      "in_the_money": false
    },
    {
      "option_type": "put",
      "expiration_date": "2026-05-22",
      "dte": 29,
      "strike": 127.0,
      "bid": 1.31,
      "ask": 2.07,
      "mid": 1.69,
      "premium_per_day": 0.058276,
      "delta_from_price": -51.96,
      "open_interest": 16,
      "volume": 6,
      "implied_volatility": 0.905274,
      "iv_vs_hv": 1.3717,
      "in_the_money": false
    },
    {
      "option_type": "put",
      "expiration_date": "2026-05-22",
      "dte": 29,
      "strike": 128.0,
      "bid": 1.4,
      "ask": 2.17,
      "mid": 1.785,
      "premium_per_day": 0.061552,
      "delta_from_price": -50.96,
      "open_interest": 18,
      "volume": 1,
      "implied_volatility": 0.901856,
      "iv_vs_hv": 1.3665,
      "in_the_money": false
    },
    {
      "option_type": "put",
      "expiration_date": "2026-05-22",
      "dte": 29,
      "strike": 129.0,
      "bid": 1.46,
      "ask": 2.07,
      "mid": 1.765,
      "premium_per_day": 0.060862,
      "delta_from_price": -49.96,
      "open_interest": 6,
      "volume": 1,
      "implied_volatility": 0.882814,
      "iv_vs_hv": 1.3377,
      "in_the_money": false
    },
    {
      "option_type": "put",
      "expiration_date": "2026-05-22",
      "dte": 29,
      "strike": 130.0,
      "bid": 1.55,
      "ask": 1.86,
      "mid": 1.705,
      "premium_per_day": 0.058793,
      "delta_from_price": -48.96,
      "open_interest": 1045,
      "volume": 31,
      "implied_volatility": 0.858644,
      "iv_vs_hv": 1.3011,
      "in_the_money": false
    },
    {
      "option_type": "put",
      "expiration_date": "2026-05-22",
      "dte": 29,
      "strike": 131.0,
      "bid": 1.66,
      "ask": 2.22,
      "mid": 1.94,
      "premium_per_day": 0.066897,
      "delta_from_price": -47.96,
      "open_interest": 5,
      "volume": 2,
      "implied_volatility": 0.872804,
      "iv_vs_hv": 1.3225,
      "in_the_money": false
    },
    {
      "option_type": "put",
      "expiration_date": "2026-05-22",
      "dte": 29,
      "strike": 132.0,
      "bid": 1.7,
      "ask": 2.37,
      "mid": 2.035,
      "premium_per_day": 0.070172,
      "delta_from_price": -46.96,
      "open_interest": 32,
      "volume": 2,
      "implied_volatility": 0.868165,
      "iv_vs_hv": 1.3155,
      "in_the_money": false
    },
    {
      "option_type": "put",
      "expiration_date": "2026-05-22",
      "dte": 29,
      "strike": 133.0,
      "bid": 1.77,
      "ask": 2.23,
      "mid": 2.0,
      "premium_per_day": 0.068966,
      "delta_from_price": -45.96,
      "open_interest": 74,
      "volume": 1,
      "implied_volatility": 0.847658,
      "iv_vs_hv": 1.2844,
      "in_the_money": false
    },
    {
      "option_type": "put",
      "expiration_date": "2026-05-22",
      "dte": 29,
      "strike": 134.0,
      "bid": 1.85,
      "ask": 2.75,
      "mid": 2.3,
      "premium_per_day": 0.07931,
      "delta_from_price": -44.96,
      "open_interest": 229,
      "volume": 3,
      "implied_volatility": 0.865968,
      "iv_vs_hv": 1.3122,
      "in_the_money": false
    },
    {
      "option_type": "put",
      "expiration_date": "2026-05-22",
      "dte": 29,
      "strike": 135.0,
      "bid": 1.98,
      "ask": 2.45,
      "mid": 2.215,
      "premium_per_day": 0.076379,
      "delta_from_price": -43.96,
      "open_interest": 864,
      "volume": 1,
      "implied_volatility": 0.839845,
      "iv_vs_hv": 1.2726,
      "in_the_money": false
    },
    {
      "option_type": "put",
      "expiration_date": "2026-05-29",
      "dte": 36,
      "strike": 125.0,
      "bid": 1.6,
      "ask": 2.09,
      "mid": 1.845,
      "premium_per_day": 0.05125,
      "delta_from_price": -53.96,
      "open_interest": 617,
      "volume": 98,
      "implied_volatility": 0.864503,
      "iv_vs_hv": 1.3099,
      "in_the_money": false
    },
    {
      "option_type": "put",
      "expiration_date": "2026-05-29",
      "dte": 36,
      "strike": 126.0,
      "bid": 0.52,
      "ask": 2.96,
      "mid": 1.74,
      "premium_per_day": 0.048333,
      "delta_from_price": -52.96,
      "open_interest": 10,
      "volume": 3,
      "implied_volatility": 0.836183,
      "iv_vs_hv": 1.267,
      "in_the_money": false
    },
    {
      "option_type": "put",
      "expiration_date": "2026-05-29",
      "dte": 36,
      "strike": 127.0,
      "bid": 0.01,
      "ask": 2.71,
      "mid": 1.36,
      "premium_per_day": 0.037778,
      "delta_from_price": -51.96,
      "open_interest": 17,
      "volume": 7,
      "implied_volatility": 0.771487,
      "iv_vs_hv": 1.169,
      "in_the_money": false
    },
    {
      "option_type": "put",
      "expiration_date": "2026-05-29",
      "dte": 36,
      "strike": 128.0,
      "bid": 0.15,
      "ask": 4.25,
      "mid": 2.2,
      "premium_per_day": 0.061111,
      "delta_from_price": -50.96,
      "open_interest": 20,
      "volume": 8,
      "implied_volatility": 0.860353,
      "iv_vs_hv": 1.3037,
      "in_the_money": false
    },
    {
      "option_type": "put",
      "expiration_date": "2026-05-29",
      "dte": 36,
      "strike": 129.0,
      "bid": 1.78,
      "ask": 2.98,
      "mid": 2.38,
      "premium_per_day": 0.066111,
      "delta_from_price": -49.96,
      "open_interest": 14,
      "volume": 4,
      "implied_volatility": 0.864503,
      "iv_vs_hv": 1.3099,
      "in_the_money": false
    },
    {
      "option_type": "put",
      "expiration_date": "2026-05-29",
      "dte": 36,
      "strike": 130.0,
      "bid": 1.91,
      "ask": 2.6,
      "mid": 2.255,
      "premium_per_day": 0.062639,
      "delta_from_price": -48.96,
      "open_interest": 281,
      "volume": 7,
      "implied_volatility": 0.835695,
      "iv_vs_hv": 1.2663,
      "in_the_money": false
    },
    {
      "option_type": "put",
      "expiration_date": "2026-05-29",
      "dte": 36,
      "strike": 131.0,
      "bid": 2.08,
      "ask": 2.9,
      "mid": 2.49,
      "premium_per_day": 0.069167,
      "delta_from_price": -47.96,
      "open_interest": 18,
      "volume": 3,
      "implied_volatility": 0.844728,
      "iv_vs_hv": 1.28,
      "in_the_money": false
    },
    {
      "option_type": "put",
      "expiration_date": "2026-05-29",
      "dte": 36,
      "strike": 132.0,
      "bid": 2.16,
      "ask": 3.1,
      "mid": 2.63,
      "premium_per_day": 0.073056,
      "delta_from_price": -46.96,
      "open_interest": 36,
      "volume": 2,
      "implied_volatility": 0.843263,
      "iv_vs_hv": 1.2778,
      "in_the_money": false
    },
    {
      "option_type": "put",
      "expiration_date": "2026-05-29",
      "dte": 36,
      "strike": 133.0,
      "bid": 2.21,
      "ask": 3.2,
      "mid": 2.705,
      "premium_per_day": 0.075139,
      "delta_from_price": -45.96,
      "open_interest": 19,
      "volume": 2,
      "implied_volatility": 0.834963,
      "iv_vs_hv": 1.2652,
      "in_the_money": false
    },
    {
      "option_type": "put",
      "expiration_date": "2026-05-29",
      "dte": 36,
      "strike": 134.0,
      "bid": 2.22,
      "ask": 3.4,
      "mid": 2.81,
      "premium_per_day": 0.078056,
      "delta_from_price": -44.96,
      "open_interest": 5,
      "volume": 1,
      "implied_volatility": 0.829225,
      "iv_vs_hv": 1.2565,
      "in_the_money": false
    },
    {
      "option_type": "put",
      "expiration_date": "2026-05-29",
      "dte": 36,
      "strike": 135.0,
      "bid": 2.39,
      "ask": 2.95,
      "mid": 2.67,
      "premium_per_day": 0.074167,
      "delta_from_price": -43.96,
      "open_interest": 98,
      "volume": 9,
      "implied_volatility": 0.800539,
      "iv_vs_hv": 1.213,
      "in_the_money": false
    },
    {
      "option_type": "put",
      "expiration_date": "2026-06-18",
      "dte": 56,
      "strike": 125.0,
      "bid": 3.0,
      "ask": 3.4,
      "mid": 3.2,
      "premium_per_day": 0.057143,
      "delta_from_price": -53.96,
      "open_interest": 5933,
      "volume": 19,
      "implied_volatility": 0.816286,
      "iv_vs_hv": 1.2369,
      "in_the_money": false
    },
    {
      "option_type": "put",
      "expiration_date": "2026-06-18",
      "dte": 56,
      "strike": 126.0,
      "bid": 3.2,
      "ask": 3.55,
      "mid": 3.375,
      "premium_per_day": 0.060268,
      "delta_from_price": -52.96,
      "open_interest": 359,
      "volume": 30,
      "implied_volatility": 0.816408,
      "iv_vs_hv": 1.2371,
      "in_the_money": false
    },
    {
      "option_type": "put",
      "expiration_date": "2026-06-18",
      "dte": 56,
      "strike": 127.0,
      "bid": 3.25,
      "ask": 3.65,
      "mid": 3.45,
      "premium_per_day": 0.061607,
      "delta_from_price": -51.96,
      "open_interest": 396,
      "volume": 87,
      "implied_volatility": 0.808352,
      "iv_vs_hv": 1.2249,
      "in_the_money": false
    },
    {
      "option_type": "put",
      "expiration_date": "2026-06-18",
      "dte": 56,
      "strike": 128.0,
      "bid": 3.4,
      "ask": 3.85,
      "mid": 3.625,
      "premium_per_day": 0.064732,
      "delta_from_price": -50.96,
      "open_interest": 176,
      "volume": 5,
      "implied_volatility": 0.807863,
      "iv_vs_hv": 1.2241,
      "in_the_money": false
    },
    {
      "option_type": "put",
      "expiration_date": "2026-06-18",
      "dte": 56,
      "strike": 129.0,
      "bid": 3.55,
      "ask": 3.95,
      "mid": 3.75,
      "premium_per_day": 0.066964,
      "delta_from_price": -49.96,
      "open_interest": 182,
      "volume": 14,
      "implied_volatility": 0.803103,
      "iv_vs_hv": 1.2169,
      "in_the_money": false
    },
    {
      "option_type": "put",
      "expiration_date": "2026-06-18",
      "dte": 56,
      "strike": 130.0,
      "bid": 3.65,
      "ask": 4.1,
      "mid": 3.875,
      "premium_per_day": 0.069196,
      "delta_from_price": -48.96,
      "open_interest": 2076,
      "volume": 78,
      "implied_volatility": 0.79822,
      "iv_vs_hv": 1.2095,
      "in_the_money": false
    },
    {
      "option_type": "put",
      "expiration_date": "2026-06-18",
      "dte": 56,
      "strike": 131.0,
      "bid": 3.9,
      "ask": 4.3,
      "mid": 4.1,
      "premium_per_day": 0.073214,
      "delta_from_price": -47.96,
      "open_interest": 217,
      "volume": 2,
      "implied_volatility": 0.800051,
      "iv_vs_hv": 1.2123,
      "in_the_money": false
    },
    {
      "option_type": "put",
      "expiration_date": "2026-06-18",
      "dte": 56,
      "strike": 132.0,
      "bid": 4.05,
      "ask": 4.45,
      "mid": 4.25,
      "premium_per_day": 0.075893,
      "delta_from_price": -46.96,
      "open_interest": 425,
      "volume": 8,
      "implied_volatility": 0.796267,
      "iv_vs_hv": 1.2065,
      "in_the_money": false
    },
    {
      "option_type": "put",
      "expiration_date": "2026-06-18",
      "dte": 56,
      "strike": 133.0,
      "bid": 4.2,
      "ask": 4.65,
      "mid": 4.425,
      "premium_per_day": 0.079018,
      "delta_from_price": -45.96,
      "open_interest": 313,
      "volume": 4,
      "implied_volatility": 0.793825,
      "iv_vs_hv": 1.2028,
      "in_the_money": false
    },
    {
      "option_type": "put",
      "expiration_date": "2026-06-18",
      "dte": 56,
      "strike": 134.0,
      "bid": 4.3,
      "ask": 4.75,
      "mid": 4.525,
      "premium_per_day": 0.080804,
      "delta_from_price": -44.96,
      "open_interest": 491,
      "volume": 1,
      "implied_volatility": 0.786257,
      "iv_vs_hv": 1.1914,
      "in_the_money": false
    },
    {
      "option_type": "put",
      "expiration_date": "2026-06-18",
      "dte": 56,
      "strike": 135.0,
      "bid": 4.6,
      "ask": 5.0,
      "mid": 4.8,
      "premium_per_day": 0.085714,
      "delta_from_price": -43.96,
      "open_interest": 2466,
      "volume": 4,
      "implied_volatility": 0.789553,
      "iv_vs_hv": 1.1964,
      "in_the_money": false
    },
    {
      "option_type": "put",
      "expiration_date": "2026-07-17",
      "dte": 85,
      "strike": 125.0,
      "bid": 5.05,
      "ask": 5.65,
      "mid": 5.35,
      "premium_per_day": 0.062941,
      "delta_from_price": -53.96,
      "open_interest": 690,
      "volume": 17,
      "implied_volatility": 0.791262,
      "iv_vs_hv": 1.199,
      "in_the_money": false
    },
    {
      "option_type": "put",
      "expiration_date": "2026-07-17",
      "dte": 85,
      "strike": 130.0,
      "bid": 6.0,
      "ask": 6.6,
      "mid": 6.3,
      "premium_per_day": 0.074118,
      "delta_from_price": -48.96,
      "open_interest": 2039,
      "volume": 16,
      "implied_volatility": 0.777834,
      "iv_vs_hv": 1.1786,
      "in_the_money": false
    },
    {
      "option_type": "put",
      "expiration_date": "2026-07-17",
      "dte": 85,
      "strike": 135.0,
      "bid": 7.2,
      "ask": 7.75,
      "mid": 7.475,
      "premium_per_day": 0.087941,
      "delta_from_price": -43.96,
      "open_interest": 671,
      "volume": 14,
      "implied_volatility": 0.769534,
      "iv_vs_hv": 1.166,
      "in_the_money": false
    },
    {
      "option_type": "put",
      "expiration_date": "2026-08-21",
      "dte": 120,
      "strike": 125.0,
      "bid": 7.8,
      "ask": 8.5,
      "mid": 8.15,
      "premium_per_day": 0.067917,
      "delta_from_price": -53.96,
      "open_interest": 784,
      "volume": 1,
      "implied_volatility": 0.787722,
      "iv_vs_hv": 1.1936,
      "in_the_money": false
    },
    {
      "option_type": "put",
      "expiration_date": "2026-08-21",
      "dte": 120,
      "strike": 130.0,
      "bid": 9.05,
      "ask": 9.75,
      "mid": 9.4,
      "premium_per_day": 0.078333,
      "delta_from_price": -48.96,
      "open_interest": 1086,
      "volume": 44,
      "implied_volatility": 0.778139,
      "iv_vs_hv": 1.1791,
      "in_the_money": false
    },
    {
      "option_type": "put",
      "expiration_date": "2026-08-21",
      "dte": 120,
      "strike": 135.0,
      "bid": 10.4,
      "ask": 11.1,
      "mid": 10.75,
      "premium_per_day": 0.089583,
      "delta_from_price": -43.96,
      "open_interest": 818,
      "volume": 28,
      "implied_volatility": 0.768069,
      "iv_vs_hv": 1.1638,
      "in_the_money": false
    },
    {
      "option_type": "put",
      "expiration_date": "2026-09-18",
      "dte": 148,
      "strike": 125.0,
      "bid": 10.05,
      "ask": 10.45,
      "mid": 10.25,
      "premium_per_day": 0.069257,
      "delta_from_price": -53.96,
      "open_interest": 710,
      "volume": 2,
      "implied_volatility": 0.785097,
      "iv_vs_hv": 1.1896,
      "in_the_money": false
    },
    {
      "option_type": "put",
      "expiration_date": "2026-09-18",
      "dte": 148,
      "strike": 130.0,
      "bid": 11.4,
      "ask": 11.8,
      "mid": 11.6,
      "premium_per_day": 0.078378,
      "delta_from_price": -48.96,
      "open_interest": 816,
      "volume": 14,
      "implied_volatility": 0.774477,
      "iv_vs_hv": 1.1735,
      "in_the_money": false
    },
    {
      "option_type": "put",
      "expiration_date": "2026-09-18",
      "dte": 148,
      "strike": 135.0,
      "bid": 12.8,
      "ask": 13.3,
      "mid": 13.05,
      "premium_per_day": 0.088176,
      "delta_from_price": -43.96,
      "open_interest": 656,
      "volume": 1,
      "implied_volatility": 0.763857,
      "iv_vs_hv": 1.1574,
      "in_the_money": false
    },
    {
      "option_type": "put",
      "expiration_date": "2026-10-16",
      "dte": 176,
      "strike": 125.0,
      "bid": 11.8,
      "ask": 12.65,
      "mid": 12.225,
      "premium_per_day": 0.06946,
      "delta_from_price": -53.96,
      "open_interest": 278,
      "volume": 28,
      "implied_volatility": 0.782595,
      "iv_vs_hv": 1.1858,
      "in_the_money": false
    },
    {
      "option_type": "put",
      "expiration_date": "2026-10-16",
      "dte": 176,
      "strike": 130.0,
      "bid": 13.4,
      "ask": 14.1,
      "mid": 13.75,
      "premium_per_day": 0.078125,
      "delta_from_price": -48.96,
      "open_interest": 332,
      "volume": 1,
      "implied_volatility": 0.774111,
      "iv_vs_hv": 1.173,
      "in_the_money": false
    },
    {
      "option_type": "put",
      "expiration_date": "2026-10-16",
      "dte": 176,
      "strike": 135.0,
      "bid": 15.15,
      "ask": 15.75,
      "mid": 15.45,
      "premium_per_day": 0.087784,
      "delta_from_price": -43.96,
      "open_interest": 299,
      "volume": 124,
      "implied_volatility": 0.767703,
      "iv_vs_hv": 1.1633,
      "in_the_money": false
    },
    {
      "option_type": "put",
      "expiration_date": "2026-11-20",
      "dte": 211,
      "strike": 125.0,
      "bid": 14.1,
      "ask": 15.7,
      "mid": 14.9,
      "premium_per_day": 0.070616,
      "delta_from_price": -53.96,
      "open_interest": 22,
      "volume": 9,
      "implied_volatility": 0.789675,
      "iv_vs_hv": 1.1966,
      "in_the_money": false
    },
    {
      "option_type": "put",
      "expiration_date": "2026-11-20",
      "dte": 211,
      "strike": 130.0,
      "bid": 15.8,
      "ask": 17.3,
      "mid": 16.55,
      "premium_per_day": 0.078436,
      "delta_from_price": -48.96,
      "open_interest": 18,
      "volume": 12,
      "implied_volatility": 0.781069,
      "iv_vs_hv": 1.1835,
      "in_the_money": false
    },
    {
      "option_type": "put",
      "expiration_date": "2026-11-20",
      "dte": 211,
      "strike": 135.0,
      "bid": 17.45,
      "ask": 19.25,
      "mid": 18.35,
      "premium_per_day": 0.086967,
      "delta_from_price": -43.96,
      "open_interest": 3,
      "volume": 2,
      "implied_volatility": 0.773928,
      "iv_vs_hv": 1.1727,
      "in_the_money": false
    },
    {
      "option_type": "put",
      "expiration_date": "2026-12-18",
      "dte": 239,
      "strike": 125.0,
      "bid": 15.9,
      "ask": 16.5,
      "mid": 16.2,
      "premium_per_day": 0.067782,
      "delta_from_price": -53.96,
      "open_interest": 609,
      "volume": 8,
      "implied_volatility": 0.775606,
      "iv_vs_hv": 1.1752,
      "in_the_money": false
    },
    {
      "option_type": "put",
      "expiration_date": "2026-12-18",
      "dte": 239,
      "strike": 130.0,
      "bid": 17.7,
      "ask": 18.25,
      "mid": 17.975,
      "premium_per_day": 0.075209,
      "delta_from_price": -48.96,
      "open_interest": 2393,
      "volume": 5,
      "implied_volatility": 0.768801,
      "iv_vs_hv": 1.1649,
      "in_the_money": false
    },
    {
      "option_type": "put",
      "expiration_date": "2026-12-18",
      "dte": 239,
      "strike": 135.0,
      "bid": 19.65,
      "ask": 20.1,
      "mid": 19.875,
      "premium_per_day": 0.083159,
      "delta_from_price": -43.96,
      "open_interest": 661,
      "volume": 26,
      "implied_volatility": 0.762789,
      "iv_vs_hv": 1.1558,
      "in_the_money": false
    },
    {
      "option_type": "put",
      "expiration_date": "2027-01-15",
      "dte": 267,
      "strike": 125.0,
      "bid": 17.65,
      "ask": 18.1,
      "mid": 17.875,
      "premium_per_day": 0.066948,
      "delta_from_price": -53.96,
      "open_interest": 624,
      "volume": 56,
      "implied_volatility": 0.774264,
      "iv_vs_hv": 1.1732,
      "in_the_money": false
    },
    {
      "option_type": "put",
      "expiration_date": "2027-01-15",
      "dte": 267,
      "strike": 130.0,
      "bid": 19.4,
      "ask": 19.95,
      "mid": 19.675,
      "premium_per_day": 0.073689,
      "delta_from_price": -48.96,
      "open_interest": 802,
      "volume": 16,
      "implied_volatility": 0.766451,
      "iv_vs_hv": 1.1614,
      "in_the_money": false
    },
    {
      "option_type": "put",
      "expiration_date": "2027-01-15",
      "dte": 267,
      "strike": 135.0,
      "bid": 21.3,
      "ask": 21.85,
      "mid": 21.575,
      "premium_per_day": 0.080805,
      "delta_from_price": -43.96,
      "open_interest": 918,
      "volume": 15,
      "implied_volatility": 0.759005,
      "iv_vs_hv": 1.1501,
      "in_the_money": false
    },
    {
      "option_type": "put",
      "expiration_date": "2027-03-19",
      "dte": 330,
      "strike": 125.0,
      "bid": 20.8,
      "ask": 22.4,
      "mid": 21.6,
      "premium_per_day": 0.065455,
      "delta_from_price": -53.96,
      "open_interest": 233,
      "volume": 1,
      "implied_volatility": 0.776217,
      "iv_vs_hv": 1.1762,
      "in_the_money": false
    },
    {
      "option_type": "put",
      "expiration_date": "2027-03-19",
      "dte": 330,
      "strike": 130.0,
      "bid": 22.4,
      "ask": 24.6,
      "mid": 23.5,
      "premium_per_day": 0.071212,
      "delta_from_price": -48.96,
      "open_interest": 56,
      "volume": 11,
      "implied_volatility": 0.767672,
      "iv_vs_hv": 1.1632,
      "in_the_money": false
    },
    {
      "option_type": "put",
      "expiration_date": "2027-03-19",
      "dte": 330,
      "strike": 135.0,
      "bid": 24.7,
      "ask": 26.75,
      "mid": 25.725,
      "premium_per_day": 0.077955,
      "delta_from_price": -43.96,
      "open_interest": 19,
      "volume": 2,
      "implied_volatility": 0.764101,
      "iv_vs_hv": 1.1578,
      "in_the_money": false
    },
    {
      "option_type": "put",
      "expiration_date": "2027-06-17",
      "dte": 420,
      "strike": 125.0,
      "bid": 25.1,
      "ask": 26.3,
      "mid": 25.7,
      "premium_per_day": 0.06119,
      "delta_from_price": -53.96,
      "open_interest": 1054,
      "volume": 1,
      "implied_volatility": 0.765078,
      "iv_vs_hv": 1.1593,
      "in_the_money": false
    },
    {
      "option_type": "put",
      "expiration_date": "2027-06-17",
      "dte": 420,
      "strike": 130.0,
      "bid": 26.9,
      "ask": 29.05,
      "mid": 27.975,
      "premium_per_day": 0.066607,
      "delta_from_price": -48.96,
      "open_interest": 174,
      "volume": 19,
      "implied_volatility": 0.761111,
      "iv_vs_hv": 1.1533,
      "in_the_money": false
    },
    {
      "option_type": "put",
      "expiration_date": "2027-06-17",
      "dte": 420,
      "strike": 135.0,
      "bid": 29.2,
      "ask": 31.1,
      "mid": 30.15,
      "premium_per_day": 0.071786,
      "delta_from_price": -43.96,
      "open_interest": 177,
      "volume": 25,
      "implied_volatility": 0.754092,
      "iv_vs_hv": 1.1426,
      "in_the_money": false
    },
    {
      "option_type": "put",
      "expiration_date": "2027-09-17",
      "dte": 512,
      "strike": 125.0,
      "bid": 29.2,
      "ask": 30.95,
      "mid": 30.075,
      "premium_per_day": 0.05874,
      "delta_from_price": -53.96,
      "open_interest": 131,
      "volume": 1,
      "implied_volatility": 0.767153,
      "iv_vs_hv": 1.1624,
      "in_the_money": false
    },
    {
      "option_type": "put",
      "expiration_date": "2027-09-17",
      "dte": 512,
      "strike": 130.0,
      "bid": 30.1,
      "ask": 33.3,
      "mid": 31.7,
      "premium_per_day": 0.061914,
      "delta_from_price": -48.96,
      "open_interest": 172,
      "volume": 3,
      "implied_volatility": 0.750216,
      "iv_vs_hv": 1.1368,
      "in_the_money": false
    },
    {
      "option_type": "put",
      "expiration_date": "2027-09-17",
      "dte": 512,
      "strike": 135.0,
      "bid": 33.8,
      "ask": 35.75,
      "mid": 34.775,
      "premium_per_day": 0.06792,
      "delta_from_price": -43.96,
      "open_interest": 47,
      "volume": 6,
      "implied_volatility": 0.755953,
      "iv_vs_hv": 1.1455,
      "in_the_money": false
    },
    {
      "option_type": "put",
      "expiration_date": "2027-12-17",
      "dte": 603,
      "strike": 125.0,
      "bid": 32.9,
      "ask": 34.45,
      "mid": 33.675,
      "premium_per_day": 0.055846,
      "delta_from_price": -53.96,
      "open_interest": 442,
      "volume": 2,
      "implied_volatility": 0.763369,
      "iv_vs_hv": 1.1567,
      "in_the_money": false
    },
    {
      "option_type": "put",
      "expiration_date": "2027-12-17",
      "dte": 603,
      "strike": 130.0,
      "bid": 35.25,
      "ask": 37.05,
      "mid": 36.15,
      "premium_per_day": 0.05995,
      "delta_from_price": -48.96,
      "open_interest": 214,
      "volume": 1,
      "implied_volatility": 0.758608,
      "iv_vs_hv": 1.1495,
      "in_the_money": false
    },
    {
      "option_type": "put",
      "expiration_date": "2027-12-17",
      "dte": 603,
      "strike": 135.0,
      "bid": 37.1,
      "ask": 39.15,
      "mid": 38.125,
      "premium_per_day": 0.063226,
      "delta_from_price": -43.96,
      "open_interest": 392,
      "volume": 1,
      "implied_volatility": 0.745669,
      "iv_vs_hv": 1.1299,
      "in_the_money": false
    },
    {
      "option_type": "put",
      "expiration_date": "2028-01-21",
      "dte": 638,
      "strike": 125.0,
      "bid": 34.05,
      "ask": 35.65,
      "mid": 34.85,
      "premium_per_day": 0.054624,
      "delta_from_price": -53.96,
      "open_interest": 103,
      "volume": 2,
      "implied_volatility": 0.760195,
      "iv_vs_hv": 1.1519,
      "in_the_money": false
    },
    {
      "option_type": "put",
      "expiration_date": "2028-01-21",
      "dte": 638,
      "strike": 130.0,
      "bid": 36.55,
      "ask": 38.35,
      "mid": 37.45,
      "premium_per_day": 0.058699,
      "delta_from_price": -48.96,
      "open_interest": 449,
      "volume": 1,
      "implied_volatility": 0.756808,
      "iv_vs_hv": 1.1468,
      "in_the_money": false
    },
    {
      "option_type": "put",
      "expiration_date": "2028-01-21",
      "dte": 638,
      "strike": 135.0,
      "bid": 37.75,
      "ask": 41.05,
      "mid": 39.4,
      "premium_per_day": 0.061755,
      "delta_from_price": -43.96,
      "open_interest": 594,
      "volume": 3,
      "implied_volatility": 0.743243,
      "iv_vs_hv": 1.1262,
      "in_the_money": false
    },
    {
      "option_type": "put",
      "expiration_date": "2028-06-16",
      "dte": 785,
      "strike": 125.0,
      "bid": 38.65,
      "ask": 40.85,
      "mid": 39.75,
      "premium_per_day": 0.050637,
      "delta_from_price": -53.96,
      "open_interest": 323,
      "volume": 2,
      "implied_volatility": 0.753665,
      "iv_vs_hv": 1.142,
      "in_the_money": false
    },
    {
      "option_type": "put",
      "expiration_date": "2028-06-16",
      "dte": 785,
      "strike": 130.0,
      "bid": 41.25,
      "ask": 43.7,
      "mid": 42.475,
      "premium_per_day": 0.054108,
      "delta_from_price": -48.96,
      "open_interest": 80,
      "volume": 1,
      "implied_volatility": 0.750125,
      "iv_vs_hv": 1.1366,
      "in_the_money": false
    },
    {
      "option_type": "put",
      "expiration_date": "2028-06-16",
      "dte": 785,
      "strike": 135.0,
      "bid": 43.85,
      "ask": 46.45,
      "mid": 45.15,
      "premium_per_day": 0.057516,
      "delta_from_price": -43.96,
      "open_interest": 54,
      "volume": 8,
      "implied_volatility": 0.745242,
      "iv_vs_hv": 1.1292,
      "in_the_money": false
    },
    {
      "option_type": "put",
      "expiration_date": "2028-12-15",
      "dte": 967,
      "strike": 125.0,
      "bid": 43.2,
      "ask": 46.55,
      "mid": 44.875,
      "premium_per_day": 0.046406,
      "delta_from_price": -53.96,
      "open_interest": 55,
      "volume": 1,
      "implied_volatility": 0.744631,
      "iv_vs_hv": 1.1283,
      "in_the_money": false
    },
    {
      "option_type": "put",
      "expiration_date": "2028-12-15",
      "dte": 967,
      "strike": 130.0,
      "bid": 45.9,
      "ask": 49.65,
      "mid": 47.775,
      "premium_per_day": 0.049405,
      "delta_from_price": -48.96,
      "open_interest": 99,
      "volume": 14,
      "implied_volatility": 0.741641,
      "iv_vs_hv": 1.1238,
      "in_the_money": false
    },
    {
      "option_type": "put",
      "expiration_date": "2028-12-15",
      "dte": 967,
      "strike": 135.0,
      "bid": 48.6,
      "ask": 52.05,
      "mid": 50.325,
      "premium_per_day": 0.052042,
      "delta_from_price": -43.96,
      "open_interest": 58,
      "volume": 16,
      "implied_volatility": 0.733828,
      "iv_vs_hv": 1.1119,
      "in_the_money": false
    }
  ]
}